Workbook
Name Treasury_API_link: Data_Link!$A$1:$A$93942

Sheet README
B2: TREASURY & LIQUIDITY MANAGEMENT MODEL
B3: Enterprise Liquidity Monitoring & 13-Week Cash Forecast
B5: MODEL PURPOSE
B6: This workbook provides enterprise-grade treasury and liquidity management for corporate finance teams.
B7: Key capabilities include:
B8: • Daily liquidity visibility across all bank accounts and legal entities
B9: • Multi-currency cash positioning with automatic FX translation
B10: • 13-week rolling cash forecast with scenario analysis
B11: • FX exposure monitoring and sensitivity testing
B12: • Interest rate sensitivity analysis
B13: • Liquidity buffer threshold monitoring and breach alerts
B15: DATA SOURCES
B16: Source | C16: Connection Type | D16: Refresh Frequency | E16: Status
B17: Bank Balances | C17: SQL / Power Query | D17: Daily | E17: ⏳ Pending Connection
B18: FX Rates | C18: API / Power Query | D18: Real-time | E18: ⏳ Pending Connection
B19: Interest Rates | C19: Bloomberg / API | D19: Daily | E19: ⏳ Pending Connection
B20: Cash Forecast | C20: FP&A System | D20: Weekly | E20: ⏳ Pending Connection
B21: Entity Master | C21: ERP System | D21: Monthly | E21: ⏳ Pending Connection
B23: REFRESH EXPECTATIONS
B24: • Cash Balances: Updated daily by 9:00 AM local time
B25: • FX Rates: Updated real-time during market hours
B26: • 13-Week Forecast: Refreshed weekly on Monday
B27: • Dashboard: Auto-calculates on data refresh
B29: COLOR LEGEND
B30: ■ BLUE | C30: Input cells - manually entered or imported data
B31: ■ BLACK | C31: Calculated cells - formulas referencing other cells
B32: ■ GREEN | C32: Output / KPI cells - cross-sheet references and key metrics
B34: ASSUMPTIONS GOVERNANCE
B35: • All model assumptions are centralized in the 'Global_Assumptions' sheet
B36: • Changes to assumptions require Treasury Manager approval
B37: • Assumption changes must be documented with date and rationale
B38: • Quarterly review of all assumptions required
B40: SHEET NAVIGATION
B41: Sheet | C41: Purpose | D41: Type
B42: Global_Assumptions | C42: Model parameters and assumptions | D42: INPUT
B43: Date_Calendar | C43: Date reference table (18+ months) | D43: REFERENCE
B44: Cash_Balances_Actuals | C44: Daily cash balances by entity/account | D44: DATA
B45: FX_Rates | C45: Currency exchange rates | D45: DATA
B46: Interest_Rates | C46: Interest rate curves | D46: DATA
B47: Cash_Inflows | C47: Forecasted cash inflows by category | D47: FORECAST
B48: Cash_Outflows | C48: Forecasted cash outflows by category | D48: FORECAST
B49: 13W_Cash_Forecast | C49: 13-week rolling cash forecast | D49: CALCULATION
B50: FX_Exposure | C50: FX exposure and sensitivity | D50: CALCULATION
B51: Liquidity_Metrics | C51: Key liquidity KPIs | D51: OUTPUT
B52: Dashboard | C52: Executive summary and charts | D52: OUTPUT
B54: VERSION CONTROL
B55: Model Version: | C55: 1
B56: Last Updated: | C56: [AUTO-REFRESH TIMESTAMP]
B57: Updated By: | C57: [USER]
B58: Next Review: | C58: [QUARTERLY]

Sheet Dashboard
B2: TREASURY & LIQUIDITY DASHBOARD | H2: Last Updated: | I2: =NOW() -> 46002.873
B3: Executive Summary
B5: LIQUIDITY STATUS
B6: Overall Status: | C6: {=Liquidity_Metrics!C30} -> ACTION REQUIRED
B7: Tests Passed: | C7: {=Liquidity_Metrics!C27} -> 4 | D7: of 6
B9: TOTAL CASH POSITION | E9: MINIMUM LIQUIDITY BUFFER | H9: BUFFER SURPLUS
B10: {=Liquidity_Metrics!C7} -> 132028400 | E10: =Global_Assumptions!C31 -> 50000000 | H10: =B10-E10 -> 82028400
B12: 13W ENDING CASH | E12: WEEKS OF COVERAGE | H12: FX RISK (10% STRESS)
B13: {=Liquidity_Metrics!C17} -> 134451060 | E13: {=Liquidity_Metrics!C9} -> 2.8397376 | F13: weeks | H13: {=Liquidity_Metrics!C12} -> 4232840
B15: 13-WEEK CASH FORECAST (USD Millions)
C16: Wk 0 | D16: Wk 1 | E16: Wk 2 | F16: Wk 3 | G16: Wk 4 | H16: Wk 5 | I16: Wk 6 | J16: Wk 7 | K16: Wk 8 | L16: Wk 9 | M16: Wk 10 | N16: Wk 11 | O16: Wk 12 | P16: Wk 13
B17: Ending Cash | C17: ='13W_Cash_Forecast'!C18/1000000 -> 89.7 | D17: ='13W_Cash_Forecast'!D18/1000000 -> 96.19666 | E17: ='13W_Cash_Forecast'!E18/1000000 -> 95.99348 | F17: ='13W_Cash_Forecast'!F18/1000000 -> 105.13376 | G17: ='13W_Cash_Forecast'!G18/1000000 -> 99.680544 | H17: ='13W_Cash_Forecast'!H18/1000000 -> 105.53254 | I17: ='13W_Cash_Forecast'!I18/1000000 -> 106.8272 | J17: ='13W_Cash_Forecast'!J18/1000000 -> 115.32282 | ... P17: ='13W_Cash_Forecast'!P18/1000000 -> 134.45106
B18: Net Movement | C18: ='13W_Cash_Forecast'!C17/1000000 -> 0 | D18: ='13W_Cash_Forecast'!D17/1000000 -> 6.49666 | E18: ='13W_Cash_Forecast'!E17/1000000 -> -0.20318 | F18: ='13W_Cash_Forecast'!F17/1000000 -> 9.140284 | G18: ='13W_Cash_Forecast'!G17/1000000 -> -5.45322 | H18: ='13W_Cash_Forecast'!H17/1000000 -> 5.851996 | I18: ='13W_Cash_Forecast'!I17/1000000 -> 1.29466 | J18: ='13W_Cash_Forecast'!J17/1000000 -> 8.49562 | ... P18: ='13W_Cash_Forecast'!P17/1000000 -> 6.49666
B19: Min Buffer | C19: =Global_Assumptions!$C$31/1000000 -> 50 | D19: =Global_Assumptions!$C$31/1000000 -> 50 | E19: =Global_Assumptions!$C$31/1000000 -> 50 | F19: =Global_Assumptions!$C$31/1000000 -> 50 | G19: =Global_Assumptions!$C$31/1000000 -> 50 | H19: =Global_Assumptions!$C$31/1000000 -> 50 | I19: =Global_Assumptions!$C$31/1000000 -> 50 | J19: =Global_Assumptions!$C$31/1000000 -> 50 | ... P19: =Global_Assumptions!$C$31/1000000 -> 50
B21: CASH BY CURRENCY | F21: 13-WEEK CASH FLOWS | I21: KEY RISK INDICATORS
B22: Currency | C22: Amount (USD) | D22: % of Total | F22: Category | G22: Amount | I22: Risk | J22: Status
B23: USD | C23: {=FX_Exposure!E7} -> 89700000 | D23: {=FX_Exposure!F7} -> 0.67939928 | F23: Total Inflows | G23: {=Liquidity_Metrics!C20} -> 649162260 | I23: Liquidity Buffer | J23: {=Liquidity_Metrics!E7} -> PASS
B24: EUR | C24: {=FX_Exposure!E8} -> 18960000 | D24: {=FX_Exposure!F8} -> 0.14360547 | F24: Total Outflows | G24: {=Liquidity_Metrics!C21} -> 604411200 | I24: Min Cash Test | J24: {=Liquidity_Metrics!E8} -> PASS
B25: GBP | C25: {=FX_Exposure!E9} -> 10216800 | D25: {=FX_Exposure!F9} -> 0.077383351 | F25: Net Cash Flow | G25: =G23-G24 -> 44751060 | I25: FX Concentration | J25: {=Liquidity_Metrics!E11} -> FAIL
B26: SGD | C26: {=FX_Exposure!E10} -> 13151600 | D26: {=FX_Exposure!F10} -> 0.099611902 | I26: FX Risk Level | J26: {=Liquidity_Metrics!E12} -> PASS
B27: Total | C27: {=FX_Exposure!E11} -> 132028400 | D27: 1

Sheet Global_Assumptions
B2: GLOBAL ASSUMPTIONS
B3: All model parameters and assumptions are centralized here
A5: x | B5: MODEL PARAMETERS
B6: Parameter | C6: Value | D6: Description
B7: Base Currency | C7: USD | D7: Reporting currency for all consolidated views
B8: Forecast Start Date | C8: =TODAY() -> 46002 | D8: Dynamic start date for forecast period
B9: Number of Forecast Weeks | C9: 13 | D9: Rolling forecast horizon (typically 13 weeks)
B10: Day Count Convention | C10: ACT/360 | D10: Interest calculation day count basis
B11: FX Translation Method | C11: Spot | D11: Spot rate or average rate for FX translation
B12: Interest Compounding | C12: Daily | D12: Compounding frequency for yield calculations
B13: Fiscal Year Start Month | C13: 1 | D13: Month number for fiscal year start (1=January)
A15: x | B15: INTEREST RATE ASSUMPTIONS
B16: Rate Type | C16: Current Rate | D16: Forecast Rate | E16: Source
B17: SOFR (Overnight) | C17: 0.0525 | D17: 0.05 | E17: Federal Reserve
B18: Fed Funds Rate | C18: 0.055 | D18: 0.0525 | E18: Federal Reserve
B19: 3-Month T-Bill | C19: 0.052 | D19: 0.05 | E19: Treasury Direct
B20: Prime Rate | C20: 0.085 | D20: 0.0825 | E20: WSJ Prime Rate
A22: x | B22: FX STRESS ASSUMPTIONS
B23: Scenario | C23: FX Shock % | D23: Description
B24: Base Case | C24: 0 | D24: No FX movement
B25: Mild Stress | C25: -0.01 | D25: 1% adverse FX movement
B26: Moderate Stress | C26: -0.05 | D26: 5% adverse FX movement
B27: Severe Stress | C27: -0.1 | D27: 10% adverse FX movement
A29: x | B29: LIQUIDITY THRESHOLDS
B30: Metric | C30: Threshold | D30: Action
B31: Minimum Liquidity Buffer | C31: 50000000 | D31: Escalate to CFO if breached
B32: Target Liquidity Buffer | C32: 100000000 | D32: Optimal operating range
B33: Maximum Cash Concentration % | C33: 0.4 | D33: Max % in single bank/currency
B34: Minimum Weeks of Coverage | C34: 4 | D34: Weeks of operating expenses covered
A36: x | B36: NAMED RANGE REFERENCES
B37: Use these cell references in formulas throughout the model:
B38: Reference | C38: Cell | D38: Current Value
B39: Base_Currency | C39: C7 | D39: {=C7} -> USD
B40: Forecast_Start | C40: C8 | D40: =C8 -> 46002
B41: Forecast_Weeks | C41: C9 | D41: {=C9} -> 13
B42: Min_Liquidity | C42: C31 | D42: {=C31} -> 50000000
B43: Target_Liquidity | C43: C32 | D43: {=C32} -> 100000000

Sheet Cash_Balances_Actuals
B2: CASH BALANCES (ACTUALS)
B3: Data connected via SQL / POWER QUERY
B5: Data Source: | C5: [Treasury Management System / Bank API - Currently Sample Data]
B6: Refresh Frequency: | C6: Daily at 9:00 AM
B7: Last Refresh: | C7: [AUTO-TIMESTAMP]
A9: x | B9: Date | C9: Legal Entity | D9: Entity Code | E9: Bank Name | F9: Account Number | G9: Account Type | H9: Currency | I9: Opening Balance | J9: Ending Balance | K9: Net Change
B10: 2025-12-09 | C10: Stripe US | D10: US001 | E10: JPMorgan Chase | F10: ****1234 | G10: Operating | H10: USD | I10: 25000000 | J10: 24500000 | K10: =J10-I10 -> -500000
B11: 2025-12-09 | C11: Stripe 2 US | D11: US001 | E11: Bank of America | F11: ****5678 | G11: Operating | H11: USD | I11: 15000000 | J11: 15200000 | K11: =J11-I11 -> 200000
B12: 2025-12-09 | C12: Stripe 3 US | D12: US001 | E12: Wells Fargo | F12: ****9012 | G12: Reserve | H12: USD | I12: 50000000 | J12: 50000000 | K12: =J12-I12 -> 0
B13: 2025-12-09 | C13: Stripe UK | D13: UK001 | E13: Barclays | F13: ****3456 | G13: Operating | H13: GBP | I13: 8000000 | J13: 7800000 | K13: =J13-I13 -> -200000
B14: 2025-12-09 | C14: Stripe 2 UK | D14: UK001 | E14: HSBC | F14: ****7890 | G14: Operating | H14: GBP | I14: 5000000 | J14: 5100000 | K14: =J14-I14 -> 100000
B15: 2025-12-09 | C15: Stripe EU | D15: EU001 | E15: Deutsche Bank | F15: ****2345 | G15: Operating | H15: EUR | I15: 12000000 | J15: 11800000 | K15: =J15-I15 -> -200000
B16: 2025-12-09 | C16: Stripe 2 EU | D16: EU001 | E16: BNP Paribas | F16: ****6789 | G16: Operating | H16: EUR | I16: 8000000 | J16: 8200000 | K16: =J16-I16 -> 200000
B17: 2025-12-09 | C17: Stripe SG | D17: SG001 | E17: DBS | F17: ****0123 | G17: Operating | H17: SGD | I17: 10000000 | J17: 9800000 | K17: =J17-I17 -> -200000
A19: x | B19: SUMMARY BY CURRENCY
B20: Currency | C20: Total Opening | D20: Total Ending | E20: Net Change
B21: USD | C21: =SUMIF($H$10:$H$17,B21,$I$10:$I$17) -> 90000000 | D21: =SUMIF($H$10:$H$17,B21,$J$10:$J$17) -> 89700000 | E21: =D21-C21 -> -300000
B22: GBP | C22: =SUMIF($H$10:$H$17,B22,$I$10:$I$17) -> 13000000 | D22: =SUMIF($H$10:$H$17,B22,$J$10:$J$17) -> 12900000 | E22: =D22-C22 -> -100000
B23: EUR | C23: =SUMIF($H$10:$H$17,B23,$I$10:$I$17) -> 20000000 | D23: =SUMIF($H$10:$H$17,B23,$J$10:$J$17) -> 20000000 | E23: =D23-C23 -> 0
B24: SGD | C24: =SUMIF($H$10:$H$17,B24,$I$10:$I$17) -> 10000000 | D24: =SUMIF($H$10:$H$17,B24,$J$10:$J$17) -> 9800000 | E24: =D24-C24 -> -200000
B25: TOTAL (Local Currency) | C25: =SUM(C21:C24) -> 133000000 | D25: =SUM(D21:D24) -> 132400000 | E25: =SUM(E21:E24) -> -600000

Sheet FX_Rates
B2: FX RATES (REFERENCE DATA)
B3: Data connected via SQL / POWER QUERY
B5: Data Source: | C5: [Bloomberg / Reuters / Central Bank API]
B6: Refresh Frequency: | C6: Real-time during market hours
B7: Last Refresh: | C7: [AUTO-TIMESTAMP]
A9: x | B9: SPOT FX RATES (vs USD)
B10: Date | C10: Currency | D10: Currency Name | E10: Rate to USD | F10: USD to Currency | G10: Source
B11: 2025-12-09 | C11: USD | D11: US Dollar | E11: 1 | F11: =1/E11 -> 1 | G11: Federal Reserve
B12: 2025-12-09 | C12: EUR | D12: Euro | E12: 0.948 | F12: =1/E12 -> 1.0548523 | G12: ECB
B13: 2025-12-09 | C13: GBP | D13: British Pound | E13: 0.792 | F13: =1/E13 -> 1.2626263 | G13: Bank of England
B14: 2025-12-09 | C14: JPY | D14: Japanese Yen | E14: 151.5 | F14: =1/E14 -> 0.0066006601 | G14: Bank of Japan
B15: 2025-12-09 | C15: CHF | D15: Swiss Franc | E15: 0.885 | F15: =1/E15 -> 1.1299435 | G15: SNB
B16: 2025-12-09 | C16: CAD | D16: Canadian Dollar | E16: 1.358 | F16: =1/E16 -> 0.73637703 | G16: Bank of Canada
B17: 2025-12-09 | C17: AUD | D17: Australian Dollar | E17: 1.538 | F17: =1/E17 -> 0.65019506 | G17: RBA
B18: 2025-12-09 | C18: SGD | D18: Singapore Dollar | E18: 1.342 | F18: =1/E18 -> 0.74515648 | G18: MAS
B19: 2025-12-09 | C19: HKD | D19: Hong Kong Dollar | E19: 7.785 | F19: =1/E19 -> 0.12845215 | G19: HKMA
B20: 2025-12-09 | C20: CNY | D20: Chinese Yuan | E20: 7.245 | F20: =1/E20 -> 0.13802622 | G20: PBOC
B21: 2025-12-09 | C21: INR | D21: Indian Rupee | E21: 84.25 | F21: =1/E21 -> 0.011869436 | G21: RBI
B22: 2025-12-09 | C22: MXN | D22: Mexican Peso | E22: 17.35 | F22: =1/E22 -> 0.057636888 | G22: Banxico
A24: x | B24: HISTORICAL FX RATES (for trending)
B25: Date | C25: EUR/USD | D25: GBP/USD | E25: USD/JPY | F25: USD/SGD
B26: 2025-12-09 | C26: 0.948 | D26: 0.792 | E26: 151.5 | F26: 1.342
B27: 2025-12-08 | C27: 0.9465 | D27: 0.7905 | E27: 151.25 | F27: 1.34
B28: 2025-12-07 | C28: 0.945 | D28: 0.789 | E28: 150.8 | F28: 1.3385
B29: 2025-12-06 | C29: 0.9445 | D29: 0.7885 | E29: 150.65 | F29: 1.337
B30: 2025-12-05 | C30: 0.944 | D30: 0.788 | E30: 150.4 | F30: 1.3355
B31: 2025-12-04 | C31: 0.943 | D31: 0.787 | E31: 150.2 | F31: 1.334
B32: 2025-12-03 | C32: 0.942 | D32: 0.786 | E32: 149.95 | F32: 1.3325
B33: 2025-12-02 | C33: 0.941 | D33: 0.785 | E33: 149.7 | F33: 1.331
B34: 2025-12-01 | C34: 0.94 | D34: 0.784 | E34: 149.45 | F34: 1.3295
B35: 2025-11-30 | C35: 0.939 | D35: 0.783 | E35: 149.2 | F35: 1.328
A37: x | B37: RATE LOOKUP
B38: Use to convert target rate to USD
B39: Currency Input: | C39: EUR
B40: Rate Lookup Result: | C40: =_xlfn.XLOOKUP(C39,C11:C22,E11:E22,"Not Found") -> 0.948
B41: Sample Formula: | C41: {=_xlfn.XLOOKUP("EUR",FX_Rates!C11:C22,FX_Rates!E11:E22)} -> 0.948

Sheet Date_Calendar
B2: DATE & CALENDAR TABLE
B3: Auto-generated from Global Assumptions
B5: Forecast Start Date | C5: {=Global_Assumptions!C8} -> 46002
B6: Forecast Weeks | C6: {=Global_Assumptions!C9} -> 13
B8: Date | C8: Day of Week | D8: Week of Year | E8: Fiscal Week | F8: Month | G8: Quarter | H8: Year | I8: Of Forecast Period?
A9: x | B9: {=Global_Assumptions!C8} -> 46002 | C9: =TEXT(B9,"dddd") -> Thursday | D9: =WEEKNUM(B9) -> 50 | E9: ="FW"&TEXT(WEEKNUM(B9),"00")&"-"&YEAR(B9) -> FW50-2025 | F9: =TEXT(B9,"mmmm") -> December | G9: ="Q"&CEILING(MONTH(B9)/3,1) -> Q4 | H9: =YEAR(B9) -> 2025 | I9: =IF(B9<=$C$5+($C$6*7),"Yes","No") -> Yes
B10: =B9+1 -> 46003 | C10: =TEXT(B10,"dddd") -> Friday | D10: =WEEKNUM(B10) -> 50 | E10: ="FW"&TEXT(WEEKNUM(B10),"00")&"-"&YEAR(B10) -> FW50-2025 | F10: =TEXT(B10,"mmmm") -> December | G10: ="Q"&CEILING(MONTH(B10)/3,1) -> Q4 | H10: =YEAR(B10) -> 2025 | I10: =IF(B10<=$C$5+($C$6*7),"Yes","No") -> Yes
B11: =B10+1 -> 46004 | C11: =TEXT(B11,"dddd") -> Saturday | D11: =WEEKNUM(B11) -> 50 | E11: ="FW"&TEXT(WEEKNUM(B11),"00")&"-"&YEAR(B11) -> FW50-2025 | F11: =TEXT(B11,"mmmm") -> December | G11: ="Q"&CEILING(MONTH(B11)/3,1) -> Q4 | H11: =YEAR(B11) -> 2025 | I11: =IF(B11<=$C$5+($C$6*7),"Yes","No") -> Yes
B12: =B11+1 -> 46005 | C12: =TEXT(B12,"dddd") -> Sunday | D12: =WEEKNUM(B12) -> 51 | E12: ="FW"&TEXT(WEEKNUM(B12),"00")&"-"&YEAR(B12) -> FW51-2025 | F12: =TEXT(B12,"mmmm") -> December | G12: ="Q"&CEILING(MONTH(B12)/3,1) -> Q4 | H12: =YEAR(B12) -> 2025 | I12: =IF(B12<=$C$5+($C$6*7),"Yes","No") -> Yes
B13: =B12+1 -> 46006 | C13: =TEXT(B13,"dddd") -> Monday | D13: =WEEKNUM(B13) -> 51 | E13: ="FW"&TEXT(WEEKNUM(B13),"00")&"-"&YEAR(B13) -> FW51-2025 | F13: =TEXT(B13,"mmmm") -> December | G13: ="Q"&CEILING(MONTH(B13)/3,1) -> Q4 | H13: =YEAR(B13) -> 2025 | I13: =IF(B13<=$C$5+($C$6*7),"Yes","No") -> Yes
B14: =B13+1 -> 46007 | C14: =TEXT(B14,"dddd") -> Tuesday | D14: =WEEKNUM(B14) -> 51 | E14: ="FW"&TEXT(WEEKNUM(B14),"00")&"-"&YEAR(B14) -> FW51-2025 | F14: =TEXT(B14,"mmmm") -> December | G14: ="Q"&CEILING(MONTH(B14)/3,1) -> Q4 | H14: =YEAR(B14) -> 2025 | I14: =IF(B14<=$C$5+($C$6*7),"Yes","No") -> Yes
B15: =B14+1 -> 46008 | C15: =TEXT(B15,"dddd") -> Wednesday | D15: =WEEKNUM(B15) -> 51 | E15: ="FW"&TEXT(WEEKNUM(B15),"00")&"-"&YEAR(B15) -> FW51-2025 | F15: =TEXT(B15,"mmmm") -> December | G15: ="Q"&CEILING(MONTH(B15)/3,1) -> Q4 | H15: =YEAR(B15) -> 2025 | I15: =IF(B15<=$C$5+($C$6*7),"Yes","No") -> Yes
A16: x | B16: =B15+1 -> 46009 | C16: =TEXT(B16,"dddd") -> Thursday | D16: =WEEKNUM(B16) -> 51 | E16: ="FW"&TEXT(WEEKNUM(B16),"00")&"-"&YEAR(B16) -> FW51-2025 | F16: =TEXT(B16,"mmmm") -> December | G16: ="Q"&CEILING(MONTH(B16)/3,1) -> Q4 | H16: =YEAR(B16) -> 2025 | I16: =IF(B16<=$C$5+($C$6*7),"Yes","No") -> Yes
B17: =B16+1 -> 46010 | C17: =TEXT(B17,"dddd") -> Friday | D17: =WEEKNUM(B17) -> 51 | E17: ="FW"&TEXT(WEEKNUM(B17),"00")&"-"&YEAR(B17) -> FW51-2025 | F17: =TEXT(B17,"mmmm") -> December | G17: ="Q"&CEILING(MONTH(B17)/3,1) -> Q4 | H17: =YEAR(B17) -> 2025 | I17: =IF(B17<=$C$5+($C$6*7),"Yes","No") -> Yes
B18: =B17+1 -> 46011 | C18: =TEXT(B18,"dddd") -> Saturday | D18: =WEEKNUM(B18) -> 51 | E18: ="FW"&TEXT(WEEKNUM(B18),"00")&"-"&YEAR(B18) -> FW51-2025 | F18: =TEXT(B18,"mmmm") -> December | G18: ="Q"&CEILING(MONTH(B18)/3,1) -> Q4 | H18: =YEAR(B18) -> 2025 | I18: =IF(B18<=$C$5+($C$6*7),"Yes","No") -> Yes
B19: =B18+1 -> 46012 | C19: =TEXT(B19,"dddd") -> Sunday | D19: =WEEKNUM(B19) -> 52 | E19: ="FW"&TEXT(WEEKNUM(B19),"00")&"-"&YEAR(B19) -> FW52-2025 | F19: =TEXT(B19,"mmmm") -> December | G19: ="Q"&CEILING(MONTH(B19)/3,1) -> Q4 | H19: =YEAR(B19) -> 2025 | I19: =IF(B19<=$C$5+($C$6*7),"Yes","No") -> Yes
B20: =B19+1 -> 46013 | C20: =TEXT(B20,"dddd") -> Monday | D20: =WEEKNUM(B20) -> 52 | E20: ="FW"&TEXT(WEEKNUM(B20),"00")&"-"&YEAR(B20) -> FW52-2025 | F20: =TEXT(B20,"mmmm") -> December | G20: ="Q"&CEILING(MONTH(B20)/3,1) -> Q4 | H20: =YEAR(B20) -> 2025 | I20: =IF(B20<=$C$5+($C$6*7),"Yes","No") -> Yes
B21: =B20+1 -> 46014 | C21: =TEXT(B21,"dddd") -> Tuesday | D21: =WEEKNUM(B21) -> 52 | E21: ="FW"&TEXT(WEEKNUM(B21),"00")&"-"&YEAR(B21) -> FW52-2025 | F21: =TEXT(B21,"mmmm") -> December | G21: ="Q"&CEILING(MONTH(B21)/3,1) -> Q4 | H21: =YEAR(B21) -> 2025 | I21: =IF(B21<=$C$5+($C$6*7),"Yes","No") -> Yes
B22: =B21+1 -> 46015 | C22: =TEXT(B22,"dddd") -> Wednesday | D22: =WEEKNUM(B22) -> 52 | E22: ="FW"&TEXT(WEEKNUM(B22),"00")&"-"&YEAR(B22) -> FW52-2025 | F22: =TEXT(B22,"mmmm") -> December | G22: ="Q"&CEILING(MONTH(B22)/3,1) -> Q4 | H22: =YEAR(B22) -> 2025 | I22: =IF(B22<=$C$5+($C$6*7),"Yes","No") -> Yes
A23: x | B23: =B22+1 -> 46016 | C23: =TEXT(B23,"dddd") -> Thursday | D23: =WEEKNUM(B23) -> 52 | E23: ="FW"&TEXT(WEEKNUM(B23),"00")&"-"&YEAR(B23) -> FW52-2025 | F23: =TEXT(B23,"mmmm") -> December | G23: ="Q"&CEILING(MONTH(B23)/3,1) -> Q4 | H23: =YEAR(B23) -> 2025 | I23: =IF(B23<=$C$5+($C$6*7),"Yes","No") -> Yes
B24: =B23+1 -> 46017 | C24: =TEXT(B24,"dddd") -> Friday | D24: =WEEKNUM(B24) -> 52 | E24: ="FW"&TEXT(WEEKNUM(B24),"00")&"-"&YEAR(B24) -> FW52-2025 | F24: =TEXT(B24,"mmmm") -> December | G24: ="Q"&CEILING(MONTH(B24)/3,1) -> Q4 | H24: =YEAR(B24) -> 2025 | I24: =IF(B24<=$C$5+($C$6*7),"Yes","No") -> Yes
B25: =B24+1 -> 46018 | C25: =TEXT(B25,"dddd") -> Saturday | D25: =WEEKNUM(B25) -> 52 | E25: ="FW"&TEXT(WEEKNUM(B25),"00")&"-"&YEAR(B25) -> FW52-2025 | F25: =TEXT(B25,"mmmm") -> December | G25: ="Q"&CEILING(MONTH(B25)/3,1) -> Q4 | H25: =YEAR(B25) -> 2025 | I25: =IF(B25<=$C$5+($C$6*7),"Yes","No") -> Yes
B26: =B25+1 -> 46019 | C26: =TEXT(B26,"dddd") -> Sunday | D26: =WEEKNUM(B26) -> 53 | E26: ="FW"&TEXT(WEEKNUM(B26),"00")&"-"&YEAR(B26) -> FW53-2025 | F26: =TEXT(B26,"mmmm") -> December | G26: ="Q"&CEILING(MONTH(B26)/3,1) -> Q4 | H26: =YEAR(B26) -> 2025 | I26: =IF(B26<=$C$5+($C$6*7),"Yes","No") -> Yes
B27: =B26+1 -> 46020 | C27: =TEXT(B27,"dddd") -> Monday | D27: =WEEKNUM(B27) -> 53 | E27: ="FW"&TEXT(WEEKNUM(B27),"00")&"-"&YEAR(B27) -> FW53-2025 | F27: =TEXT(B27,"mmmm") -> December | G27: ="Q"&CEILING(MONTH(B27)/3,1) -> Q4 | H27: =YEAR(B27) -> 2025 | I27: =IF(B27<=$C$5+($C$6*7),"Yes","No") -> Yes
B28: =B27+1 -> 46021 | C28: =TEXT(B28,"dddd") -> Tuesday | D28: =WEEKNUM(B28) -> 53 | E28: ="FW"&TEXT(WEEKNUM(B28),"00")&"-"&YEAR(B28) -> FW53-2025 | F28: =TEXT(B28,"mmmm") -> December | G28: ="Q"&CEILING(MONTH(B28)/3,1) -> Q4 | H28: =YEAR(B28) -> 2025 | I28: =IF(B28<=$C$5+($C$6*7),"Yes","No") -> Yes
B29: =B28+1 -> 46022 | C29: =TEXT(B29,"dddd") -> Wednesday | D29: =WEEKNUM(B29) -> 53 | E29: ="FW"&TEXT(WEEKNUM(B29),"00")&"-"&YEAR(B29) -> FW53-2025 | F29: =TEXT(B29,"mmmm") -> December | G29: ="Q"&CEILING(MONTH(B29)/3,1) -> Q4 | H29: =YEAR(B29) -> 2025 | I29: =IF(B29<=$C$5+($C$6*7),"Yes","No") -> Yes
A30: x | B30: =B29+1 -> 46023 | C30: =TEXT(B30,"dddd") -> Thursday | D30: =WEEKNUM(B30) -> 1 | E30: ="FW"&TEXT(WEEKNUM(B30),"00")&"-"&YEAR(B30) -> FW01-2026 | F30: =TEXT(B30,"mmmm") -> January | G30: ="Q"&CEILING(MONTH(B30)/3,1) -> Q1 | H30: =YEAR(B30) -> 2026 | I30: =IF(B30<=$C$5+($C$6*7),"Yes","No") -> Yes
B31: =B30+1 -> 46024 | C31: =TEXT(B31,"dddd") -> Friday | D31: =WEEKNUM(B31) -> 1 | E31: ="FW"&TEXT(WEEKNUM(B31),"00")&"-"&YEAR(B31) -> FW01-2026 | F31: =TEXT(B31,"mmmm") -> January | G31: ="Q"&CEILING(MONTH(B31)/3,1) -> Q1 | H31: =YEAR(B31) -> 2026 | I31: =IF(B31<=$C$5+($C$6*7),"Yes","No") -> Yes
B32: =B31+1 -> 46025 | C32: =TEXT(B32,"dddd") -> Saturday | D32: =WEEKNUM(B32) -> 1 | E32: ="FW"&TEXT(WEEKNUM(B32),"00")&"-"&YEAR(B32) -> FW01-2026 | F32: =TEXT(B32,"mmmm") -> January | G32: ="Q"&CEILING(MONTH(B32)/3,1) -> Q1 | H32: =YEAR(B32) -> 2026 | I32: =IF(B32<=$C$5+($C$6*7),"Yes","No") -> Yes
B33: =B32+1 -> 46026 | C33: =TEXT(B33,"dddd") -> Sunday | D33: =WEEKNUM(B33) -> 2 | E33: ="FW"&TEXT(WEEKNUM(B33),"00")&"-"&YEAR(B33) -> FW02-2026 | F33: =TEXT(B33,"mmmm") -> January | G33: ="Q"&CEILING(MONTH(B33)/3,1) -> Q1 | H33: =YEAR(B33) -> 2026 | I33: =IF(B33<=$C$5+($C$6*7),"Yes","No") -> Yes
B34: =B33+1 -> 46027 | C34: =TEXT(B34,"dddd") -> Monday | D34: =WEEKNUM(B34) -> 2 | E34: ="FW"&TEXT(WEEKNUM(B34),"00")&"-"&YEAR(B34) -> FW02-2026 | F34: =TEXT(B34,"mmmm") -> January | G34: ="Q"&CEILING(MONTH(B34)/3,1) -> Q1 | H34: =YEAR(B34) -> 2026 | I34: =IF(B34<=$C$5+($C$6*7),"Yes","No") -> Yes
B35: =B34+1 -> 46028 | C35: =TEXT(B35,"dddd") -> Tuesday | D35: =WEEKNUM(B35) -> 2 | E35: ="FW"&TEXT(WEEKNUM(B35),"00")&"-"&YEAR(B35) -> FW02-2026 | F35: =TEXT(B35,"mmmm") -> January | G35: ="Q"&CEILING(MONTH(B35)/3,1) -> Q1 | H35: =YEAR(B35) -> 2026 | I35: =IF(B35<=$C$5+($C$6*7),"Yes","No") -> Yes
B36: =B35+1 -> 46029 | C36: =TEXT(B36,"dddd") -> Wednesday | D36: =WEEKNUM(B36) -> 2 | E36: ="FW"&TEXT(WEEKNUM(B36),"00")&"-"&YEAR(B36) -> FW02-2026 | F36: =TEXT(B36,"mmmm") -> January | G36: ="Q"&CEILING(MONTH(B36)/3,1) -> Q1 | H36: =YEAR(B36) -> 2026 | I36: =IF(B36<=$C$5+($C$6*7),"Yes","No") -> Yes
A37: x | B37: =B36+1 -> 46030 | C37: =TEXT(B37,"dddd") -> Thursday | D37: =WEEKNUM(B37) -> 2 | E37: ="FW"&TEXT(WEEKNUM(B37),"00")&"-"&YEAR(B37) -> FW02-2026 | F37: =TEXT(B37,"mmmm") -> January | G37: ="Q"&CEILING(MONTH(B37)/3,1) -> Q1 | H37: =YEAR(B37) -> 2026 | I37: =IF(B37<=$C$5+($C$6*7),"Yes","No") -> Yes
B38: =B37+1 -> 46031 | C38: =TEXT(B38,"dddd") -> Friday | D38: =WEEKNUM(B38) -> 2 | E38: ="FW"&TEXT(WEEKNUM(B38),"00")&"-"&YEAR(B38) -> FW02-2026 | F38: =TEXT(B38,"mmmm") -> January | G38: ="Q"&CEILING(MONTH(B38)/3,1) -> Q1 | H38: =YEAR(B38) -> 2026 | I38: =IF(B38<=$C$5+($C$6*7),"Yes","No") -> Yes
B39: =B38+1 -> 46032 | C39: =TEXT(B39,"dddd") -> Saturday | D39: =WEEKNUM(B39) -> 2 | E39: ="FW"&TEXT(WEEKNUM(B39),"00")&"-"&YEAR(B39) -> FW02-2026 | F39: =TEXT(B39,"mmmm") -> January | G39: ="Q"&CEILING(MONTH(B39)/3,1) -> Q1 | H39: =YEAR(B39) -> 2026 | I39: =IF(B39<=$C$5+($C$6*7),"Yes","No") -> Yes
B40: =B39+1 -> 46033 | C40: =TEXT(B40,"dddd") -> Sunday | D40: =WEEKNUM(B40) -> 3 | E40: ="FW"&TEXT(WEEKNUM(B40),"00")&"-"&YEAR(B40) -> FW03-2026 | F40: =TEXT(B40,"mmmm") -> January | G40: ="Q"&CEILING(MONTH(B40)/3,1) -> Q1 | H40: =YEAR(B40) -> 2026 | I40: =IF(B40<=$C$5+($C$6*7),"Yes","No") -> Yes
B41: =B40+1 -> 46034 | C41: =TEXT(B41,"dddd") -> Monday | D41: =WEEKNUM(B41) -> 3 | E41: ="FW"&TEXT(WEEKNUM(B41),"00")&"-"&YEAR(B41) -> FW03-2026 | F41: =TEXT(B41,"mmmm") -> January | G41: ="Q"&CEILING(MONTH(B41)/3,1) -> Q1 | H41: =YEAR(B41) -> 2026 | I41: =IF(B41<=$C$5+($C$6*7),"Yes","No") -> Yes
B42: =B41+1 -> 46035 | C42: =TEXT(B42,"dddd") -> Tuesday | D42: =WEEKNUM(B42) -> 3 | E42: ="FW"&TEXT(WEEKNUM(B42),"00")&"-"&YEAR(B42) -> FW03-2026 | F42: =TEXT(B42,"mmmm") -> January | G42: ="Q"&CEILING(MONTH(B42)/3,1) -> Q1 | H42: =YEAR(B42) -> 2026 | I42: =IF(B42<=$C$5+($C$6*7),"Yes","No") -> Yes
B43: =B42+1 -> 46036 | C43: =TEXT(B43,"dddd") -> Wednesday | D43: =WEEKNUM(B43) -> 3 | E43: ="FW"&TEXT(WEEKNUM(B43),"00")&"-"&YEAR(B43) -> FW03-2026 | F43: =TEXT(B43,"mmmm") -> January | G43: ="Q"&CEILING(MONTH(B43)/3,1) -> Q1 | H43: =YEAR(B43) -> 2026 | I43: =IF(B43<=$C$5+($C$6*7),"Yes","No") -> Yes
A44: x | B44: =B43+1 -> 46037 | C44: =TEXT(B44,"dddd") -> Thursday | D44: =WEEKNUM(B44) -> 3 | E44: ="FW"&TEXT(WEEKNUM(B44),"00")&"-"&YEAR(B44) -> FW03-2026 | F44: =TEXT(B44,"mmmm") -> January | G44: ="Q"&CEILING(MONTH(B44)/3,1) -> Q1 | H44: =YEAR(B44) -> 2026 | I44: =IF(B44<=$C$5+($C$6*7),"Yes","No") -> Yes
B45: =B44+1 -> 46038 | C45: =TEXT(B45,"dddd") -> Friday | D45: =WEEKNUM(B45) -> 3 | E45: ="FW"&TEXT(WEEKNUM(B45),"00")&"-"&YEAR(B45) -> FW03-2026 | F45: =TEXT(B45,"mmmm") -> January | G45: ="Q"&CEILING(MONTH(B45)/3,1) -> Q1 | H45: =YEAR(B45) -> 2026 | I45: =IF(B45<=$C$5+($C$6*7),"Yes","No") -> Yes
B46: =B45+1 -> 46039 | C46: =TEXT(B46,"dddd") -> Saturday | D46: =WEEKNUM(B46) -> 3 | E46: ="FW"&TEXT(WEEKNUM(B46),"00")&"-"&YEAR(B46) -> FW03-2026 | F46: =TEXT(B46,"mmmm") -> January | G46: ="Q"&CEILING(MONTH(B46)/3,1) -> Q1 | H46: =YEAR(B46) -> 2026 | I46: =IF(B46<=$C$5+($C$6*7),"Yes","No") -> Yes
B47: =B46+1 -> 46040 | C47: =TEXT(B47,"dddd") -> Sunday | D47: =WEEKNUM(B47) -> 4 | E47: ="FW"&TEXT(WEEKNUM(B47),"00")&"-"&YEAR(B47) -> FW04-2026 | F47: =TEXT(B47,"mmmm") -> January | G47: ="Q"&CEILING(MONTH(B47)/3,1) -> Q1 | H47: =YEAR(B47) -> 2026 | I47: =IF(B47<=$C$5+($C$6*7),"Yes","No") -> Yes
B48: =B47+1 -> 46041 | C48: =TEXT(B48,"dddd") -> Monday | D48: =WEEKNUM(B48) -> 4 | E48: ="FW"&TEXT(WEEKNUM(B48),"00")&"-"&YEAR(B48) -> FW04-2026 | F48: =TEXT(B48,"mmmm") -> January | G48: ="Q"&CEILING(MONTH(B48)/3,1) -> Q1 | H48: =YEAR(B48) -> 2026 | I48: =IF(B48<=$C$5+($C$6*7),"Yes","No") -> Yes
B49: =B48+1 -> 46042 | C49: =TEXT(B49,"dddd") -> Tuesday | D49: =WEEKNUM(B49) -> 4 | E49: ="FW"&TEXT(WEEKNUM(B49),"00")&"-"&YEAR(B49) -> FW04-2026 | F49: =TEXT(B49,"mmmm") -> January | G49: ="Q"&CEILING(MONTH(B49)/3,1) -> Q1 | H49: =YEAR(B49) -> 2026 | I49: =IF(B49<=$C$5+($C$6*7),"Yes","No") -> Yes
B50: =B49+1 -> 46043 | C50: =TEXT(B50,"dddd") -> Wednesday | D50: =WEEKNUM(B50) -> 4 | E50: ="FW"&TEXT(WEEKNUM(B50),"00")&"-"&YEAR(B50) -> FW04-2026 | F50: =TEXT(B50,"mmmm") -> January | G50: ="Q"&CEILING(MONTH(B50)/3,1) -> Q1 | H50: =YEAR(B50) -> 2026 | I50: =IF(B50<=$C$5+($C$6*7),"Yes","No") -> Yes
A51: x | B51: =B50+1 -> 46044 | C51: =TEXT(B51,"dddd") -> Thursday | D51: =WEEKNUM(B51) -> 4 | E51: ="FW"&TEXT(WEEKNUM(B51),"00")&"-"&YEAR(B51) -> FW04-2026 | F51: =TEXT(B51,"mmmm") -> January | G51: ="Q"&CEILING(MONTH(B51)/3,1) -> Q1 | H51: =YEAR(B51) -> 2026 | I51: =IF(B51<=$C$5+($C$6*7),"Yes","No") -> Yes
B52: =B51+1 -> 46045 | C52: =TEXT(B52,"dddd") -> Friday | D52: =WEEKNUM(B52) -> 4 | E52: ="FW"&TEXT(WEEKNUM(B52),"00")&"-"&YEAR(B52) -> FW04-2026 | F52: =TEXT(B52,"mmmm") -> January | G52: ="Q"&CEILING(MONTH(B52)/3,1) -> Q1 | H52: =YEAR(B52) -> 2026 | I52: =IF(B52<=$C$5+($C$6*7),"Yes","No") -> Yes
B53: =B52+1 -> 46046 | C53: =TEXT(B53,"dddd") -> Saturday | D53: =WEEKNUM(B53) -> 4 | E53: ="FW"&TEXT(WEEKNUM(B53),"00")&"-"&YEAR(B53) -> FW04-2026 | F53: =TEXT(B53,"mmmm") -> January | G53: ="Q"&CEILING(MONTH(B53)/3,1) -> Q1 | H53: =YEAR(B53) -> 2026 | I53: =IF(B53<=$C$5+($C$6*7),"Yes","No") -> Yes
B54: =B53+1 -> 46047 | C54: =TEXT(B54,"dddd") -> Sunday | D54: =WEEKNUM(B54) -> 5 | E54: ="FW"&TEXT(WEEKNUM(B54),"00")&"-"&YEAR(B54) -> FW05-2026 | F54: =TEXT(B54,"mmmm") -> January | G54: ="Q"&CEILING(MONTH(B54)/3,1) -> Q1 | H54: =YEAR(B54) -> 2026 | I54: =IF(B54<=$C$5+($C$6*7),"Yes","No") -> Yes
B55: =B54+1 -> 46048 | C55: =TEXT(B55,"dddd") -> Monday | D55: =WEEKNUM(B55) -> 5 | E55: ="FW"&TEXT(WEEKNUM(B55),"00")&"-"&YEAR(B55) -> FW05-2026 | F55: =TEXT(B55,"mmmm") -> January | G55: ="Q"&CEILING(MONTH(B55)/3,1) -> Q1 | H55: =YEAR(B55) -> 2026 | I55: =IF(B55<=$C$5+($C$6*7),"Yes","No") -> Yes
B56: =B55+1 -> 46049 | C56: =TEXT(B56,"dddd") -> Tuesday | D56: =WEEKNUM(B56) -> 5 | E56: ="FW"&TEXT(WEEKNUM(B56),"00")&"-"&YEAR(B56) -> FW05-2026 | F56: =TEXT(B56,"mmmm") -> January | G56: ="Q"&CEILING(MONTH(B56)/3,1) -> Q1 | H56: =YEAR(B56) -> 2026 | I56: =IF(B56<=$C$5+($C$6*7),"Yes","No") -> Yes
B57: =B56+1 -> 46050 | C57: =TEXT(B57,"dddd") -> Wednesday | D57: =WEEKNUM(B57) -> 5 | E57: ="FW"&TEXT(WEEKNUM(B57),"00")&"-"&YEAR(B57) -> FW05-2026 | F57: =TEXT(B57,"mmmm") -> January | G57: ="Q"&CEILING(MONTH(B57)/3,1) -> Q1 | H57: =YEAR(B57) -> 2026 | I57: =IF(B57<=$C$5+($C$6*7),"Yes","No") -> Yes
A58: x | B58: =B57+1 -> 46051 | C58: =TEXT(B58,"dddd") -> Thursday | D58: =WEEKNUM(B58) -> 5 | E58: ="FW"&TEXT(WEEKNUM(B58),"00")&"-"&YEAR(B58) -> FW05-2026 | F58: =TEXT(B58,"mmmm") -> January | G58: ="Q"&CEILING(MONTH(B58)/3,1) -> Q1 | H58: =YEAR(B58) -> 2026 | I58: =IF(B58<=$C$5+($C$6*7),"Yes","No") -> Yes
B59: =B58+1 -> 46052 | C59: =TEXT(B59,"dddd") -> Friday | D59: =WEEKNUM(B59) -> 5 | E59: ="FW"&TEXT(WEEKNUM(B59),"00")&"-"&YEAR(B59) -> FW05-2026 | F59: =TEXT(B59,"mmmm") -> January | G59: ="Q"&CEILING(MONTH(B59)/3,1) -> Q1 | H59: =YEAR(B59) -> 2026 | I59: =IF(B59<=$C$5+($C$6*7),"Yes","No") -> Yes
B60: =B59+1 -> 46053 | C60: =TEXT(B60,"dddd") -> Saturday | D60: =WEEKNUM(B60) -> 5 | E60: ="FW"&TEXT(WEEKNUM(B60),"00")&"-"&YEAR(B60) -> FW05-2026 | F60: =TEXT(B60,"mmmm") -> January | G60: ="Q"&CEILING(MONTH(B60)/3,1) -> Q1 | H60: =YEAR(B60) -> 2026 | I60: =IF(B60<=$C$5+($C$6*7),"Yes","No") -> Yes
B61: =B60+1 -> 46054 | C61: =TEXT(B61,"dddd") -> Sunday | D61: =WEEKNUM(B61) -> 6 | E61: ="FW"&TEXT(WEEKNUM(B61),"00")&"-"&YEAR(B61) -> FW06-2026 | F61: =TEXT(B61,"mmmm") -> February | G61: ="Q"&CEILING(MONTH(B61)/3,1) -> Q1 | H61: =YEAR(B61) -> 2026 | I61: =IF(B61<=$C$5+($C$6*7),"Yes","No") -> Yes
B62: =B61+1 -> 46055 | C62: =TEXT(B62,"dddd") -> Monday | D62: =WEEKNUM(B62) -> 6 | E62: ="FW"&TEXT(WEEKNUM(B62),"00")&"-"&YEAR(B62) -> FW06-2026 | F62: =TEXT(B62,"mmmm") -> February | G62: ="Q"&CEILING(MONTH(B62)/3,1) -> Q1 | H62: =YEAR(B62) -> 2026 | I62: =IF(B62<=$C$5+($C$6*7),"Yes","No") -> Yes
B63: =B62+1 -> 46056 | C63: =TEXT(B63,"dddd") -> Tuesday | D63: =WEEKNUM(B63) -> 6 | E63: ="FW"&TEXT(WEEKNUM(B63),"00")&"-"&YEAR(B63) -> FW06-2026 | F63: =TEXT(B63,"mmmm") -> February | G63: ="Q"&CEILING(MONTH(B63)/3,1) -> Q1 | H63: =YEAR(B63) -> 2026 | I63: =IF(B63<=$C$5+($C$6*7),"Yes","No") -> Yes
B64: =B63+1 -> 46057 | C64: =TEXT(B64,"dddd") -> Wednesday | D64: =WEEKNUM(B64) -> 6 | E64: ="FW"&TEXT(WEEKNUM(B64),"00")&"-"&YEAR(B64) -> FW06-2026 | F64: =TEXT(B64,"mmmm") -> February | G64: ="Q"&CEILING(MONTH(B64)/3,1) -> Q1 | H64: =YEAR(B64) -> 2026 | I64: =IF(B64<=$C$5+($C$6*7),"Yes","No") -> Yes
A65: x | B65: =B64+1 -> 46058 | C65: =TEXT(B65,"dddd") -> Thursday | D65: =WEEKNUM(B65) -> 6 | E65: ="FW"&TEXT(WEEKNUM(B65),"00")&"-"&YEAR(B65) -> FW06-2026 | F65: =TEXT(B65,"mmmm") -> February | G65: ="Q"&CEILING(MONTH(B65)/3,1) -> Q1 | H65: =YEAR(B65) -> 2026 | I65: =IF(B65<=$C$5+($C$6*7),"Yes","No") -> Yes
B66: =B65+1 -> 46059 | C66: =TEXT(B66,"dddd") -> Friday | D66: =WEEKNUM(B66) -> 6 | E66: ="FW"&TEXT(WEEKNUM(B66),"00")&"-"&YEAR(B66) -> FW06-2026 | F66: =TEXT(B66,"mmmm") -> February | G66: ="Q"&CEILING(MONTH(B66)/3,1) -> Q1 | H66: =YEAR(B66) -> 2026 | I66: =IF(B66<=$C$5+($C$6*7),"Yes","No") -> Yes
B67: =B66+1 -> 46060 | C67: =TEXT(B67,"dddd") -> Saturday | D67: =WEEKNUM(B67) -> 6 | E67: ="FW"&TEXT(WEEKNUM(B67),"00")&"-"&YEAR(B67) -> FW06-2026 | F67: =TEXT(B67,"mmmm") -> February | G67: ="Q"&CEILING(MONTH(B67)/3,1) -> Q1 | H67: =YEAR(B67) -> 2026 | I67: =IF(B67<=$C$5+($C$6*7),"Yes","No") -> Yes
B68: =B67+1 -> 46061 | C68: =TEXT(B68,"dddd") -> Sunday | D68: =WEEKNUM(B68) -> 7 | E68: ="FW"&TEXT(WEEKNUM(B68),"00")&"-"&YEAR(B68) -> FW07-2026 | F68: =TEXT(B68,"mmmm") -> February | G68: ="Q"&CEILING(MONTH(B68)/3,1) -> Q1 | H68: =YEAR(B68) -> 2026 | I68: =IF(B68<=$C$5+($C$6*7),"Yes","No") -> Yes
B69: =B68+1 -> 46062 | C69: =TEXT(B69,"dddd") -> Monday | D69: =WEEKNUM(B69) -> 7 | E69: ="FW"&TEXT(WEEKNUM(B69),"00")&"-"&YEAR(B69) -> FW07-2026 | F69: =TEXT(B69,"mmmm") -> February | G69: ="Q"&CEILING(MONTH(B69)/3,1) -> Q1 | H69: =YEAR(B69) -> 2026 | I69: =IF(B69<=$C$5+($C$6*7),"Yes","No") -> Yes
B70: =B69+1 -> 46063 | C70: =TEXT(B70,"dddd") -> Tuesday | D70: =WEEKNUM(B70) -> 7 | E70: ="FW"&TEXT(WEEKNUM(B70),"00")&"-"&YEAR(B70) -> FW07-2026 | F70: =TEXT(B70,"mmmm") -> February | G70: ="Q"&CEILING(MONTH(B70)/3,1) -> Q1 | H70: =YEAR(B70) -> 2026 | I70: =IF(B70<=$C$5+($C$6*7),"Yes","No") -> Yes
B71: =B70+1 -> 46064 | C71: =TEXT(B71,"dddd") -> Wednesday | D71: =WEEKNUM(B71) -> 7 | E71: ="FW"&TEXT(WEEKNUM(B71),"00")&"-"&YEAR(B71) -> FW07-2026 | F71: =TEXT(B71,"mmmm") -> February | G71: ="Q"&CEILING(MONTH(B71)/3,1) -> Q1 | H71: =YEAR(B71) -> 2026 | I71: =IF(B71<=$C$5+($C$6*7),"Yes","No") -> Yes
A72: x | B72: =B71+1 -> 46065 | C72: =TEXT(B72,"dddd") -> Thursday | D72: =WEEKNUM(B72) -> 7 | E72: ="FW"&TEXT(WEEKNUM(B72),"00")&"-"&YEAR(B72) -> FW07-2026 | F72: =TEXT(B72,"mmmm") -> February | G72: ="Q"&CEILING(MONTH(B72)/3,1) -> Q1 | H72: =YEAR(B72) -> 2026 | I72: =IF(B72<=$C$5+($C$6*7),"Yes","No") -> Yes
B73: =B72+1 -> 46066 | C73: =TEXT(B73,"dddd") -> Friday | D73: =WEEKNUM(B73) -> 7 | E73: ="FW"&TEXT(WEEKNUM(B73),"00")&"-"&YEAR(B73) -> FW07-2026 | F73: =TEXT(B73,"mmmm") -> February | G73: ="Q"&CEILING(MONTH(B73)/3,1) -> Q1 | H73: =YEAR(B73) -> 2026 | I73: =IF(B73<=$C$5+($C$6*7),"Yes","No") -> Yes
B74: =B73+1 -> 46067 | C74: =TEXT(B74,"dddd") -> Saturday | D74: =WEEKNUM(B74) -> 7 | E74: ="FW"&TEXT(WEEKNUM(B74),"00")&"-"&YEAR(B74) -> FW07-2026 | F74: =TEXT(B74,"mmmm") -> February | G74: ="Q"&CEILING(MONTH(B74)/3,1) -> Q1 | H74: =YEAR(B74) -> 2026 | I74: =IF(B74<=$C$5+($C$6*7),"Yes","No") -> Yes
B75: =B74+1 -> 46068 | C75: =TEXT(B75,"dddd") -> Sunday | D75: =WEEKNUM(B75) -> 8 | E75: ="FW"&TEXT(WEEKNUM(B75),"00")&"-"&YEAR(B75) -> FW08-2026 | F75: =TEXT(B75,"mmmm") -> February | G75: ="Q"&CEILING(MONTH(B75)/3,1) -> Q1 | H75: =YEAR(B75) -> 2026 | I75: =IF(B75<=$C$5+($C$6*7),"Yes","No") -> Yes
B76: =B75+1 -> 46069 | C76: =TEXT(B76,"dddd") -> Monday | D76: =WEEKNUM(B76) -> 8 | E76: ="FW"&TEXT(WEEKNUM(B76),"00")&"-"&YEAR(B76) -> FW08-2026 | F76: =TEXT(B76,"mmmm") -> February | G76: ="Q"&CEILING(MONTH(B76)/3,1) -> Q1 | H76: =YEAR(B76) -> 2026 | I76: =IF(B76<=$C$5+($C$6*7),"Yes","No") -> Yes
B77: =B76+1 -> 46070 | C77: =TEXT(B77,"dddd") -> Tuesday | D77: =WEEKNUM(B77) -> 8 | E77: ="FW"&TEXT(WEEKNUM(B77),"00")&"-"&YEAR(B77) -> FW08-2026 | F77: =TEXT(B77,"mmmm") -> February | G77: ="Q"&CEILING(MONTH(B77)/3,1) -> Q1 | H77: =YEAR(B77) -> 2026 | I77: =IF(B77<=$C$5+($C$6*7),"Yes","No") -> Yes
B78: =B77+1 -> 46071 | C78: =TEXT(B78,"dddd") -> Wednesday | D78: =WEEKNUM(B78) -> 8 | E78: ="FW"&TEXT(WEEKNUM(B78),"00")&"-"&YEAR(B78) -> FW08-2026 | F78: =TEXT(B78,"mmmm") -> February | G78: ="Q"&CEILING(MONTH(B78)/3,1) -> Q1 | H78: =YEAR(B78) -> 2026 | I78: =IF(B78<=$C$5+($C$6*7),"Yes","No") -> Yes
A79: x | B79: =B78+1 -> 46072 | C79: =TEXT(B79,"dddd") -> Thursday | D79: =WEEKNUM(B79) -> 8 | E79: ="FW"&TEXT(WEEKNUM(B79),"00")&"-"&YEAR(B79) -> FW08-2026 | F79: =TEXT(B79,"mmmm") -> February | G79: ="Q"&CEILING(MONTH(B79)/3,1) -> Q1 | H79: =YEAR(B79) -> 2026 | I79: =IF(B79<=$C$5+($C$6*7),"Yes","No") -> Yes
B80: =B79+1 -> 46073 | C80: =TEXT(B80,"dddd") -> Friday | D80: =WEEKNUM(B80) -> 8 | E80: ="FW"&TEXT(WEEKNUM(B80),"00")&"-"&YEAR(B80) -> FW08-2026 | F80: =TEXT(B80,"mmmm") -> February | G80: ="Q"&CEILING(MONTH(B80)/3,1) -> Q1 | H80: =YEAR(B80) -> 2026 | I80: =IF(B80<=$C$5+($C$6*7),"Yes","No") -> Yes
B81: =B80+1 -> 46074 | C81: =TEXT(B81,"dddd") -> Saturday | D81: =WEEKNUM(B81) -> 8 | E81: ="FW"&TEXT(WEEKNUM(B81),"00")&"-"&YEAR(B81) -> FW08-2026 | F81: =TEXT(B81,"mmmm") -> February | G81: ="Q"&CEILING(MONTH(B81)/3,1) -> Q1 | H81: =YEAR(B81) -> 2026 | I81: =IF(B81<=$C$5+($C$6*7),"Yes","No") -> Yes
B82: =B81+1 -> 46075 | C82: =TEXT(B82,"dddd") -> Sunday | D82: =WEEKNUM(B82) -> 9 | E82: ="FW"&TEXT(WEEKNUM(B82),"00")&"-"&YEAR(B82) -> FW09-2026 | F82: =TEXT(B82,"mmmm") -> February | G82: ="Q"&CEILING(MONTH(B82)/3,1) -> Q1 | H82: =YEAR(B82) -> 2026 | I82: =IF(B82<=$C$5+($C$6*7),"Yes","No") -> Yes
B83: =B82+1 -> 46076 | C83: =TEXT(B83,"dddd") -> Monday | D83: =WEEKNUM(B83) -> 9 | E83: ="FW"&TEXT(WEEKNUM(B83),"00")&"-"&YEAR(B83) -> FW09-2026 | F83: =TEXT(B83,"mmmm") -> February | G83: ="Q"&CEILING(MONTH(B83)/3,1) -> Q1 | H83: =YEAR(B83) -> 2026 | I83: =IF(B83<=$C$5+($C$6*7),"Yes","No") -> Yes
B84: =B83+1 -> 46077 | C84: =TEXT(B84,"dddd") -> Tuesday | D84: =WEEKNUM(B84) -> 9 | E84: ="FW"&TEXT(WEEKNUM(B84),"00")&"-"&YEAR(B84) -> FW09-2026 | F84: =TEXT(B84,"mmmm") -> February | G84: ="Q"&CEILING(MONTH(B84)/3,1) -> Q1 | H84: =YEAR(B84) -> 2026 | I84: =IF(B84<=$C$5+($C$6*7),"Yes","No") -> Yes
B85: =B84+1 -> 46078 | C85: =TEXT(B85,"dddd") -> Wednesday | D85: =WEEKNUM(B85) -> 9 | E85: ="FW"&TEXT(WEEKNUM(B85),"00")&"-"&YEAR(B85) -> FW09-2026 | F85: =TEXT(B85,"mmmm") -> February | G85: ="Q"&CEILING(MONTH(B85)/3,1) -> Q1 | H85: =YEAR(B85) -> 2026 | I85: =IF(B85<=$C$5+($C$6*7),"Yes","No") -> Yes
A86: x | B86: =B85+1 -> 46079 | C86: =TEXT(B86,"dddd") -> Thursday | D86: =WEEKNUM(B86) -> 9 | E86: ="FW"&TEXT(WEEKNUM(B86),"00")&"-"&YEAR(B86) -> FW09-2026 | F86: =TEXT(B86,"mmmm") -> February | G86: ="Q"&CEILING(MONTH(B86)/3,1) -> Q1 | H86: =YEAR(B86) -> 2026 | I86: =IF(B86<=$C$5+($C$6*7),"Yes","No") -> Yes
B87: =B86+1 -> 46080 | C87: =TEXT(B87,"dddd") -> Friday | D87: =WEEKNUM(B87) -> 9 | E87: ="FW"&TEXT(WEEKNUM(B87),"00")&"-"&YEAR(B87) -> FW09-2026 | F87: =TEXT(B87,"mmmm") -> February | G87: ="Q"&CEILING(MONTH(B87)/3,1) -> Q1 | H87: =YEAR(B87) -> 2026 | I87: =IF(B87<=$C$5+($C$6*7),"Yes","No") -> Yes
B88: =B87+1 -> 46081 | C88: =TEXT(B88,"dddd") -> Saturday | D88: =WEEKNUM(B88) -> 9 | E88: ="FW"&TEXT(WEEKNUM(B88),"00")&"-"&YEAR(B88) -> FW09-2026 | F88: =TEXT(B88,"mmmm") -> February | G88: ="Q"&CEILING(MONTH(B88)/3,1) -> Q1 | H88: =YEAR(B88) -> 2026 | I88: =IF(B88<=$C$5+($C$6*7),"Yes","No") -> Yes
B89: =B88+1 -> 46082 | C89: =TEXT(B89,"dddd") -> Sunday | D89: =WEEKNUM(B89) -> 10 | E89: ="FW"&TEXT(WEEKNUM(B89),"00")&"-"&YEAR(B89) -> FW10-2026 | F89: =TEXT(B89,"mmmm") -> March | G89: ="Q"&CEILING(MONTH(B89)/3,1) -> Q1 | H89: =YEAR(B89) -> 2026 | I89: =IF(B89<=$C$5+($C$6*7),"Yes","No") -> Yes
B90: =B89+1 -> 46083 | C90: =TEXT(B90,"dddd") -> Monday | D90: =WEEKNUM(B90) -> 10 | E90: ="FW"&TEXT(WEEKNUM(B90),"00")&"-"&YEAR(B90) -> FW10-2026 | F90: =TEXT(B90,"mmmm") -> March | G90: ="Q"&CEILING(MONTH(B90)/3,1) -> Q1 | H90: =YEAR(B90) -> 2026 | I90: =IF(B90<=$C$5+($C$6*7),"Yes","No") -> Yes
B91: =B90+1 -> 46084 | C91: =TEXT(B91,"dddd") -> Tuesday | D91: =WEEKNUM(B91) -> 10 | E91: ="FW"&TEXT(WEEKNUM(B91),"00")&"-"&YEAR(B91) -> FW10-2026 | F91: =TEXT(B91,"mmmm") -> March | G91: ="Q"&CEILING(MONTH(B91)/3,1) -> Q1 | H91: =YEAR(B91) -> 2026 | I91: =IF(B91<=$C$5+($C$6*7),"Yes","No") -> Yes
B92: =B91+1 -> 46085 | C92: =TEXT(B92,"dddd") -> Wednesday | D92: =WEEKNUM(B92) -> 10 | E92: ="FW"&TEXT(WEEKNUM(B92),"00")&"-"&YEAR(B92) -> FW10-2026 | F92: =TEXT(B92,"mmmm") -> March | G92: ="Q"&CEILING(MONTH(B92)/3,1) -> Q1 | H92: =YEAR(B92) -> 2026 | I92: =IF(B92<=$C$5+($C$6*7),"Yes","No") -> Yes
A93: x | B93: =B92+1 -> 46086 | C93: =TEXT(B93,"dddd") -> Thursday | D93: =WEEKNUM(B93) -> 10 | E93: ="FW"&TEXT(WEEKNUM(B93),"00")&"-"&YEAR(B93) -> FW10-2026 | F93: =TEXT(B93,"mmmm") -> March | G93: ="Q"&CEILING(MONTH(B93)/3,1) -> Q1 | H93: =YEAR(B93) -> 2026 | I93: =IF(B93<=$C$5+($C$6*7),"Yes","No") -> Yes
B94: =B93+1 -> 46087 | C94: =TEXT(B94,"dddd") -> Friday | D94: =WEEKNUM(B94) -> 10 | E94: ="FW"&TEXT(WEEKNUM(B94),"00")&"-"&YEAR(B94) -> FW10-2026 | F94: =TEXT(B94,"mmmm") -> March | G94: ="Q"&CEILING(MONTH(B94)/3,1) -> Q1 | H94: =YEAR(B94) -> 2026 | I94: =IF(B94<=$C$5+($C$6*7),"Yes","No") -> Yes
B95: =B94+1 -> 46088 | C95: =TEXT(B95,"dddd") -> Saturday | D95: =WEEKNUM(B95) -> 10 | E95: ="FW"&TEXT(WEEKNUM(B95),"00")&"-"&YEAR(B95) -> FW10-2026 | F95: =TEXT(B95,"mmmm") -> March | G95: ="Q"&CEILING(MONTH(B95)/3,1) -> Q1 | H95: =YEAR(B95) -> 2026 | I95: =IF(B95<=$C$5+($C$6*7),"Yes","No") -> Yes
B96: =B95+1 -> 46089 | C96: =TEXT(B96,"dddd") -> Sunday | D96: =WEEKNUM(B96) -> 11 | E96: ="FW"&TEXT(WEEKNUM(B96),"00")&"-"&YEAR(B96) -> FW11-2026 | F96: =TEXT(B96,"mmmm") -> March | G96: ="Q"&CEILING(MONTH(B96)/3,1) -> Q1 | H96: =YEAR(B96) -> 2026 | I96: =IF(B96<=$C$5+($C$6*7),"Yes","No") -> Yes
B97: =B96+1 -> 46090 | C97: =TEXT(B97,"dddd") -> Monday | D97: =WEEKNUM(B97) -> 11 | E97: ="FW"&TEXT(WEEKNUM(B97),"00")&"-"&YEAR(B97) -> FW11-2026 | F97: =TEXT(B97,"mmmm") -> March | G97: ="Q"&CEILING(MONTH(B97)/3,1) -> Q1 | H97: =YEAR(B97) -> 2026 | I97: =IF(B97<=$C$5+($C$6*7),"Yes","No") -> Yes
B98: =B97+1 -> 46091 | C98: =TEXT(B98,"dddd") -> Tuesday | D98: =WEEKNUM(B98) -> 11 | E98: ="FW"&TEXT(WEEKNUM(B98),"00")&"-"&YEAR(B98) -> FW11-2026 | F98: =TEXT(B98,"mmmm") -> March | G98: ="Q"&CEILING(MONTH(B98)/3,1) -> Q1 | H98: =YEAR(B98) -> 2026 | I98: =IF(B98<=$C$5+($C$6*7),"Yes","No") -> Yes
B99: =B98+1 -> 46092 | C99: =TEXT(B99,"dddd") -> Wednesday | D99: =WEEKNUM(B99) -> 11 | E99: ="FW"&TEXT(WEEKNUM(B99),"00")&"-"&YEAR(B99) -> FW11-2026 | F99: =TEXT(B99,"mmmm") -> March | G99: ="Q"&CEILING(MONTH(B99)/3,1) -> Q1 | H99: =YEAR(B99) -> 2026 | I99: =IF(B99<=$C$5+($C$6*7),"Yes","No") -> Yes
A100: x | B100: =B99+1 -> 46093 | C100: =TEXT(B100,"dddd") -> Thursday | D100: =WEEKNUM(B100) -> 11 | E100: ="FW"&TEXT(WEEKNUM(B100),"00")&"-"&YEAR(B100) -> FW11-2026 | F100: =TEXT(B100,"mmmm") -> March | G100: ="Q"&CEILING(MONTH(B100)/3,1) -> Q1 | H100: =YEAR(B100) -> 2026 | I100: =IF(B100<=$C$5+($C$6*7),"Yes","No") -> Yes
B101: =B100+1 -> 46094 | C101: =TEXT(B101,"dddd") -> Friday | D101: =WEEKNUM(B101) -> 11 | E101: ="FW"&TEXT(WEEKNUM(B101),"00")&"-"&YEAR(B101) -> FW11-2026 | F101: =TEXT(B101,"mmmm") -> March | G101: ="Q"&CEILING(MONTH(B101)/3,1) -> Q1 | H101: =YEAR(B101) -> 2026 | I101: =IF(B101<=$C$5+($C$6*7),"Yes","No") -> No
B102: =B101+1 -> 46095 | C102: =TEXT(B102,"dddd") -> Saturday | D102: =WEEKNUM(B102) -> 11 | E102: ="FW"&TEXT(WEEKNUM(B102),"00")&"-"&YEAR(B102) -> FW11-2026 | F102: =TEXT(B102,"mmmm") -> March | G102: ="Q"&CEILING(MONTH(B102)/3,1) -> Q1 | H102: =YEAR(B102) -> 2026 | I102: =IF(B102<=$C$5+($C$6*7),"Yes","No") -> No
B103: =B102+1 -> 46096 | C103: =TEXT(B103,"dddd") -> Sunday | D103: =WEEKNUM(B103) -> 12 | E103: ="FW"&TEXT(WEEKNUM(B103),"00")&"-"&YEAR(B103) -> FW12-2026 | F103: =TEXT(B103,"mmmm") -> March | G103: ="Q"&CEILING(MONTH(B103)/3,1) -> Q1 | H103: =YEAR(B103) -> 2026 | I103: =IF(B103<=$C$5+($C$6*7),"Yes","No") -> No
...

Sheet Liquidity_Metrics
B2: LIQUIDITY & RISK METRICS
A5: x | B5: KEY LIQUIDITY METRICS
B6: Metric | C6: Current Value | D6: Threshold | E6: Status
B7: Total Available Liquidity | C7: {=FX_Exposure!E11} -> 132028400 | D7: {=Global_Assumptions!C31} -> 50000000 | E7: =IF(C7>=D7,"PASS","FAIL") -> PASS
B8: Minimum Forecasted Cash | C8: =MIN('13W_Cash_Forecast'!C18:P18) -> 89700000 | D8: {=Global_Assumptions!C31} -> 50000000 | E8: =IF(C8>=D8,"PASS","FAIL") -> PASS
B9: Weeks of Liquidity Coverage | C9: =IFERROR(C7/(('13W_Cash_Forecast'!G7)/13),0) -> 2.8397376 | D9: {=Global_Assumptions!C34} -> 4 | E9: =IF(C9>=D9,"PASS","FAIL") -> FAIL
B10: Liquidity Buffer Utilization % | C10: =IFERROR(C7/Global_Assumptions!C32,0) -> 1.320284 | D10: >100% | E10: =IF(C10>=1,"PASS","WATCH") -> PASS
B11: Max Currency Concentration | C11: =MAX(FX_Exposure!D24:D27) -> 0.67939928 | D11: {=Global_Assumptions!C33} -> 0.4 | E11: =IF(C11<=D11,"PASS","FAIL") -> FAIL
B12: FX Risk Exposure (10% stress) | C12: {=FX_Exposure!G18} -> 4232840 | D12: =C7*0.05 -> 6601420 | E12: =IF(C12<=D12,"PASS","WATCH") -> PASS
A14: x | B14: 13-WEEK CASH TRAJECTORY SUMMARY
B15: Metric | C15: Value
B16: Starting Cash (Week 0) | C16: {='13W_Cash_Forecast'!C18} -> 89700000
B17: Ending Cash (Week 13) | C17: {='13W_Cash_Forecast'!P18} -> 134451060
B18: Net Change | C18: =C17-C16 -> 44751060
B19: Net Change % | C19: =IFERROR(C18/C16,0) -> 0.49889699
B20: Total 13W Inflows | C20: {='13W_Cash_Forecast'!G6} -> 649162260
B21: Total 13W Outflows | C21: {='13W_Cash_Forecast'!G7} -> 604411200
B22: Minimum Cash in Period | C22: =MIN('13W_Cash_Forecast'!C18:P18) -> 89700000
B23: Maximum Cash in Period | C23: =MAX('13W_Cash_Forecast'!C18:P18) -> 134451060
B24: Average Weekly Cash | C24: =AVERAGE('13W_Cash_Forecast'!C18:P18) -> 1.1140297e+08
B26: RISK SUMMARY
B27: Tests Passed: | C27: =COUNTIF(E7:E12,"PASS") -> 4
B28: Tests Failed: | C28: =COUNTIF(E7:E12,"FAIL") -> 2
B29: Watch Items: | C29: =COUNTIF(E7:E12,"WATCH") -> 0
B30: Overall Status: | C30: =IF(C28>0,"ACTION REQUIRED",IF(C29>0,"MONITOR","HEALTHY")) -> ACTION REQUIRED

Sheet Interest_Rates
B2: INTEREST RATES (REFERENCE DATA)
B3: Data connected via SQL / POWER QUERY
B5: Data Source: | C5: [Bloomberg / Federal Reserve API]
B6: Refresh Frequency: | C6: Daily
B7: Last Refresh: | C7: [AUTO-TIMESTAMP]
B9: CURRENT BENCHMARK RATES
B10: Date | C10: Rate Type | D10: Description | E10: Rate (%) | F10: Rate (Decimal) | G10: Source
B11: 2025-12-09 | C11: SOFR | D11: Secured Overnight Financing Rate | E11: 0.0525 | F11: {=E11} -> 0.0525 | G11: Federal Reserve
B12: 2025-12-09 | C12: EFFR | D12: Effective Federal Funds Rate | E12: 0.055 | F12: {=E12} -> 0.055 | G12: Federal Reserve
B13: 2025-12-09 | C13: OBFR | D13: Overnight Bank Funding Rate | E13: 0.054 | F13: {=E13} -> 0.054 | G13: Federal Reserve
B14: 2025-12-09 | C14: PRIME | D14: US Prime Rate | E14: 0.085 | F14: {=E14} -> 0.085 | G14: WSJ Prime Rate
B15: 2025-12-09 | C15: 3M_TBILL | D15: 3-Month Treasury Bill | E15: 0.052 | F15: {=E15} -> 0.052 | G15: Treasury Direct
B16: 2025-12-09 | C16: 6M_TBILL | D16: 6-Month Treasury Bill | E16: 0.0505 | F16: {=E16} -> 0.0505 | G16: Treasury Direct
B17: 2025-12-09 | C17: 1Y_TBILL | D17: 1-Year Treasury Bill | E17: 0.0485 | F17: {=E17} -> 0.0485 | G17: Treasury Direct
B18: 2025-12-09 | C18: 10Y_TSY | D18: 10-Year Treasury | E18: 0.0445 | F18: {=E18} -> 0.0445 | G18: Treasury Direct
B19: 2025-12-09 | C19: LIBOR_1M | D19: 1-Month Term SOFR | E19: 0.0528 | F19: {=E19} -> 0.0528 | G19: CME Group
B20: 2025-12-09 | C20: LIBOR_3M | D20: 3-Month Term SOFR | E20: 0.0535 | F20: {=E20} -> 0.0535 | G20: CME Group
B22: HISTORICAL SOFR RATES (for trending)
B23: Date | C23: SOFR | D23: Fed Funds | E23: 3M T-Bill | F23: Prime
B24: 2025-12-09 | C24: 0.0525 | D24: 0.055 | E24: 0.052 | F24: 0.085
B25: 2025-12-08 | C25: 0.0525 | D25: 0.055 | E25: 0.0518 | F25: 0.085
B26: 2025-12-07 | C26: 0.0523 | D26: 0.055 | E26: 0.0515 | F26: 0.085
B27: 2025-12-06 | C27: 0.0523 | D27: 0.055 | E27: 0.0512 | F27: 0.085
B28: 2025-12-05 | C28: 0.052 | D28: 0.055 | E28: 0.051 | F28: 0.085
B29: 2025-12-04 | C29: 0.052 | D29: 0.055 | E29: 0.0508 | F29: 0.085
B30: 2025-12-03 | C30: 0.0518 | D30: 0.055 | E30: 0.0505 | F30: 0.085
B31: 2025-12-02 | C31: 0.0518 | D31: 0.055 | E31: 0.0502 | F31: 0.085
B32: 2025-12-01 | C32: 0.0515 | D32: 0.055 | E32: 0.05 | F32: 0.085
B33: 2025-11-30 | C33: 0.0515 | D33: 0.055 | E33: 0.0498 | F33: 0.085
B35: YIELD CALCULATION HELPER
B36: Use for cash drag and yield estimation:
B37: Principal Amount: | C37: 100000000
B38: Investment Rate: | C38: {=E11} -> 0.0525
B39: Days Invested: | C39: 30
B40: Day Count (ACT/360): | C40: 360
B41: Estimated Interest: | C41: =C37*C38*(C39/C40) -> 437500
B42: Annualized Yield: | C42: {=C38} -> 0.0525
B44: RATE LOOKUP HELPER
B45: Rate Type Input: | C45: SOFR
B46: Rate Lookup Result: | C46: {=_xlfn.XLOOKUP(C45,C11:C20,E11:E20,"Not Found")} -> 0.0525

Sheet Cash_Inflows
B2: CASH INFLOWS (FORECAST)
B3: Data connected via SQL / POWER QUERY
B5: Data Source: | D5: [FP&A Forecast System / Revenue Model]
B6: Refresh Frequency: | D6: Weekly (Monday)
B7: Last Refresh: | D7: [AUTO-TIMESTAMP]
B9: Week # | C9: Week Start Date | D9: Week End Date | E9: Category | F9: Sub-Category | G9: Currency | H9: Amount (Local) | I9: FX Rate | J9: Amount (USD)
A10: x | B10: 1 | C10: =Global_Assumptions!$C$8+((B10-1)*7) -> 46002 | D10: =C10+6 -> 46008 | E10: Customer Collections | F10: Recurring Revenue | G10: USD | H10: 14850000 | I10: =IFERROR(_xlfn.XLOOKUP(G10,FX_Rates!$C$11:$C$22,FX_Rates!$E$11:$E$22),1) -> 1 | J10: =H10*I10 -> 14850000
B11: 1 | C11: =Global_Assumptions!$C$8+((B11-1)*7) -> 46002 | D11: =C11+6 -> 46008 | E11: Customer Collections | F11: One-time Payments | G11: USD | H11: 2970000 | I11: =IFERROR(_xlfn.XLOOKUP(G11,FX_Rates!$C$11:$C$22,FX_Rates!$E$11:$E$22),1) -> 1 | J11: =H11*I11 -> 2970000 | M11: SUMMARY BY WEEK
B12: 1 | C12: =Global_Assumptions!$C$8+((B12-1)*7) -> 46002 | D12: =C12+6 -> 46008 | E12: Settlement Inflows | F12: Merchant Settlements | G12: USD | H12: 24750000 | I12: =IFERROR(_xlfn.XLOOKUP(G12,FX_Rates!$C$11:$C$22,FX_Rates!$E$11:$E$22),1) -> 1 | J12: =H12*I12 -> 24750000 | M12: Week | N12: Total Inflows (USD)
B13: 1 | C13: =Global_Assumptions!$C$8+((B13-1)*7) -> 46002 | D13: =C13+6 -> 46008 | E13: Settlement Inflows | F13: Partner Settlements | G13: EUR | H13: 4950000 | I13: =IFERROR(_xlfn.XLOOKUP(G13,FX_Rates!$C$11:$C$22,FX_Rates!$E$11:$E$22),1) -> 0.948 | J13: =H13*I13 -> 4692600 | M13: 1 | N13: =SUMIF($B$10:$B$100,M13,$J$10:$J$100) -> 49474260
B14: 1 | C14: =Global_Assumptions!$C$8+((B14-1)*7) -> 46002 | D14: =C14+6 -> 46008 | E14: Interest Income | F14: Money Market | G14: USD | H14: 148500 | I14: =IFERROR(_xlfn.XLOOKUP(G14,FX_Rates!$C$11:$C$22,FX_Rates!$E$11:$E$22),1) -> 1 | J14: =H14*I14 -> 148500 | M14: 2 | N14: =SUMIF($B$10:$B$100,M14,$J$10:$J$100) -> 50473740
B15: 1 | C15: =Global_Assumptions!$C$8+((B15-1)*7) -> 46002 | D15: =C15+6 -> 46008 | E15: Other Inflows | F15: Tax Refunds | G15: USD | H15: 495000 | I15: =IFERROR(_xlfn.XLOOKUP(G15,FX_Rates!$C$11:$C$22,FX_Rates!$E$11:$E$22),1) -> 1 | J15: =H15*I15 -> 495000 | M15: 3 | N15: =SUMIF($B$10:$B$100,M15,$J$10:$J$100) -> 51473220
B16: 1 | C16: =Global_Assumptions!$C$8+((B16-1)*7) -> 46002 | D16: =C16+6 -> 46008 | E16: Customer Collections | F16: International Revenue | G16: GBP | H16: 1980000 | I16: =IFERROR(_xlfn.XLOOKUP(G16,FX_Rates!$C$11:$C$22,FX_Rates!$E$11:$E$22),1) -> 0.792 | J16: =H16*I16 -> 1568160 | M16: 4 | N16: =SUMIF($B$10:$B$100,M16,$J$10:$J$100) -> 48474780
A17: x | B17: 2 | C17: =Global_Assumptions!$C$8+((B17-1)*7) -> 46009 | D17: =C17+6 -> 46015 | E17: Customer Collections | F17: Recurring Revenue | G17: USD | H17: 15150000 | I17: =IFERROR(_xlfn.XLOOKUP(G17,FX_Rates!$C$11:$C$22,FX_Rates!$E$11:$E$22),1) -> 1 | J17: =H17*I17 -> 15150000 | M17: 5 | N17: =SUMIF($B$10:$B$100,M17,$J$10:$J$100) -> 49474260
B18: 2 | C18: =Global_Assumptions!$C$8+((B18-1)*7) -> 46009 | D18: =C18+6 -> 46015 | E18: Customer Collections | F18: One-time Payments | G18: USD | H18: 3030000 | I18: =IFERROR(_xlfn.XLOOKUP(G18,FX_Rates!$C$11:$C$22,FX_Rates!$E$11:$E$22),1) -> 1 | J18: =H18*I18 -> 3030000 | M18: 6 | N18: =SUMIF($B$10:$B$100,M18,$J$10:$J$100) -> 50473740
B19: 2 | C19: =Global_Assumptions!$C$8+((B19-1)*7) -> 46009 | D19: =C19+6 -> 46015 | E19: Settlement Inflows | F19: Merchant Settlements | G19: USD | H19: 25250000 | I19: =IFERROR(_xlfn.XLOOKUP(G19,FX_Rates!$C$11:$C$22,FX_Rates!$E$11:$E$22),1) -> 1 | J19: =H19*I19 -> 25250000 | M19: 7 | N19: =SUMIF($B$10:$B$100,M19,$J$10:$J$100) -> 51473220
B20: 2 | C20: =Global_Assumptions!$C$8+((B20-1)*7) -> 46009 | D20: =C20+6 -> 46015 | E20: Settlement Inflows | F20: Partner Settlements | G20: EUR | H20: 5050000 | I20: =IFERROR(_xlfn.XLOOKUP(G20,FX_Rates!$C$11:$C$22,FX_Rates!$E$11:$E$22),1) -> 0.948 | J20: =H20*I20 -> 4787400 | M20: 8 | N20: =SUMIF($B$10:$B$100,M20,$J$10:$J$100) -> 48474780
B21: 2 | C21: =Global_Assumptions!$C$8+((B21-1)*7) -> 46009 | D21: =C21+6 -> 46015 | E21: Interest Income | F21: Money Market | G21: USD | H21: 151500 | I21: =IFERROR(_xlfn.XLOOKUP(G21,FX_Rates!$C$11:$C$22,FX_Rates!$E$11:$E$22),1) -> 1 | J21: =H21*I21 -> 151500 | M21: 9 | N21: =SUMIF($B$10:$B$100,M21,$J$10:$J$100) -> 49474260
B22: 2 | C22: =Global_Assumptions!$C$8+((B22-1)*7) -> 46009 | D22: =C22+6 -> 46015 | E22: Other Inflows | F22: Tax Refunds | G22: USD | H22: 505000 | I22: =IFERROR(_xlfn.XLOOKUP(G22,FX_Rates!$C$11:$C$22,FX_Rates!$E$11:$E$22),1) -> 1 | J22: =H22*I22 -> 505000 | M22: 10 | N22: =SUMIF($B$10:$B$100,M22,$J$10:$J$100) -> 50473740
B23: 2 | C23: =Global_Assumptions!$C$8+((B23-1)*7) -> 46009 | D23: =C23+6 -> 46015 | E23: Customer Collections | F23: International Revenue | G23: GBP | H23: 2020000 | I23: =IFERROR(_xlfn.XLOOKUP(G23,FX_Rates!$C$11:$C$22,FX_Rates!$E$11:$E$22),1) -> 0.792 | J23: =H23*I23 -> 1599840 | M23: 11 | N23: =SUMIF($B$10:$B$100,M23,$J$10:$J$100) -> 51473220
A24: x | B24: 3 | C24: =Global_Assumptions!$C$8+((B24-1)*7) -> 46016 | D24: =C24+6 -> 46022 | E24: Customer Collections | F24: Recurring Revenue | G24: USD | H24: 15450000 | I24: =IFERROR(_xlfn.XLOOKUP(G24,FX_Rates!$C$11:$C$22,FX_Rates!$E$11:$E$22),1) -> 1 | J24: =H24*I24 -> 15450000 | M24: 12 | N24: =SUMIF($B$10:$B$100,M24,$J$10:$J$100) -> 48474780
B25: 3 | C25: =Global_Assumptions!$C$8+((B25-1)*7) -> 46016 | D25: =C25+6 -> 46022 | E25: Customer Collections | F25: One-time Payments | G25: USD | H25: 3090000 | I25: =IFERROR(_xlfn.XLOOKUP(G25,FX_Rates!$C$11:$C$22,FX_Rates!$E$11:$E$22),1) -> 1 | J25: =H25*I25 -> 3090000 | M25: 13 | N25: =SUMIF($B$10:$B$100,M25,$J$10:$J$100) -> 49474260
B26: 3 | C26: =Global_Assumptions!$C$8+((B26-1)*7) -> 46016 | D26: =C26+6 -> 46022 | E26: Settlement Inflows | F26: Merchant Settlements | G26: USD | H26: 25750000 | I26: =IFERROR(_xlfn.XLOOKUP(G26,FX_Rates!$C$11:$C$22,FX_Rates!$E$11:$E$22),1) -> 1 | J26: =H26*I26 -> 25750000 | M26: TOTAL | N26: =SUM(N13:N25) -> 649162260
B27: 3 | C27: =Global_Assumptions!$C$8+((B27-1)*7) -> 46016 | D27: =C27+6 -> 46022 | E27: Settlement Inflows | F27: Partner Settlements | G27: EUR | H27: 5150000 | I27: =IFERROR(_xlfn.XLOOKUP(G27,FX_Rates!$C$11:$C$22,FX_Rates!$E$11:$E$22),1) -> 0.948 | J27: =H27*I27 -> 4882200
B28: 3 | C28: =Global_Assumptions!$C$8+((B28-1)*7) -> 46016 | D28: =C28+6 -> 46022 | E28: Interest Income | F28: Money Market | G28: USD | H28: 154500 | I28: =IFERROR(_xlfn.XLOOKUP(G28,FX_Rates!$C$11:$C$22,FX_Rates!$E$11:$E$22),1) -> 1 | J28: =H28*I28 -> 154500 | M28: SUMMARY BY CATEGORY
B29: 3 | C29: =Global_Assumptions!$C$8+((B29-1)*7) -> 46016 | D29: =C29+6 -> 46022 | E29: Other Inflows | F29: Tax Refunds | G29: USD | H29: 515000 | I29: =IFERROR(_xlfn.XLOOKUP(G29,FX_Rates!$C$11:$C$22,FX_Rates!$E$11:$E$22),1) -> 1 | J29: =H29*I29 -> 515000 | M29: Category | N29: Total (USD) | O29: % of Total
B30: 3 | C30: =Global_Assumptions!$C$8+((B30-1)*7) -> 46016 | D30: =C30+6 -> 46022 | E30: Customer Collections | F30: International Revenue | G30: GBP | H30: 2060000 | I30: =IFERROR(_xlfn.XLOOKUP(G30,FX_Rates!$C$11:$C$22,FX_Rates!$E$11:$E$22),1) -> 0.792 | J30: =H30*I30 -> 1631520 | M30: Customer Collections | N30: =SUMIF($E$10:$E$100,M30,$J$10:$J$100) -> 254396160 | O30: =N30/$N$34 -> 0.39188378
A31: x | B31: 4 | C31: =Global_Assumptions!$C$8+((B31-1)*7) -> 46023 | D31: =C31+6 -> 46029 | E31: Customer Collections | F31: Recurring Revenue | G31: USD | H31: 14550000 | I31: =IFERROR(_xlfn.XLOOKUP(G31,FX_Rates!$C$11:$C$22,FX_Rates!$E$11:$E$22),1) -> 1 | J31: =H31*I31 -> 14550000 | M31: Settlement Inflows | N31: =SUMIF($E$10:$E$100,M31,$J$10:$J$100) -> 386322600 | O31: =N31/$N$34 -> 0.59510946
B32: 4 | C32: =Global_Assumptions!$C$8+((B32-1)*7) -> 46023 | D32: =C32+6 -> 46029 | E32: Customer Collections | F32: One-time Payments | G32: USD | H32: 2910000 | I32: =IFERROR(_xlfn.XLOOKUP(G32,FX_Rates!$C$11:$C$22,FX_Rates!$E$11:$E$22),1) -> 1 | J32: =H32*I32 -> 2910000 | M32: Interest Income | N32: =SUMIF($E$10:$E$100,M32,$J$10:$J$100) -> 1948500 | O32: =N32/$N$34 -> 0.0030015608
B33: 4 | C33: =Global_Assumptions!$C$8+((B33-1)*7) -> 46023 | D33: =C33+6 -> 46029 | E33: Settlement Inflows | F33: Merchant Settlements | G33: USD | H33: 24250000 | I33: =IFERROR(_xlfn.XLOOKUP(G33,FX_Rates!$C$11:$C$22,FX_Rates!$E$11:$E$22),1) -> 1 | J33: =H33*I33 -> 24250000 | M33: Other Inflows | N33: =SUMIF($E$10:$E$100,M33,$J$10:$J$100) -> 6495000 | O33: =N33/$N$34 -> 0.010005203
B34: 4 | C34: =Global_Assumptions!$C$8+((B34-1)*7) -> 46023 | D34: =C34+6 -> 46029 | E34: Settlement Inflows | F34: Partner Settlements | G34: EUR | H34: 4850000 | I34: =IFERROR(_xlfn.XLOOKUP(G34,FX_Rates!$C$11:$C$22,FX_Rates!$E$11:$E$22),1) -> 0.948 | J34: =H34*I34 -> 4597800 | M34: TOTAL | N34: =SUM(N30:N33) -> 649162260 | O34: 1
B35: 4 | C35: =Global_Assumptions!$C$8+((B35-1)*7) -> 46023 | D35: =C35+6 -> 46029 | E35: Interest Income | F35: Money Market | G35: USD | H35: 145500 | I35: =IFERROR(_xlfn.XLOOKUP(G35,FX_Rates!$C$11:$C$22,FX_Rates!$E$11:$E$22),1) -> 1 | J35: =H35*I35 -> 145500
B36: 4 | C36: =Global_Assumptions!$C$8+((B36-1)*7) -> 46023 | D36: =C36+6 -> 46029 | E36: Other Inflows | F36: Tax Refunds | G36: USD | H36: 485000 | I36: =IFERROR(_xlfn.XLOOKUP(G36,FX_Rates!$C$11:$C$22,FX_Rates!$E$11:$E$22),1) -> 1 | J36: =H36*I36 -> 485000
B37: 4 | C37: =Global_Assumptions!$C$8+((B37-1)*7) -> 46023 | D37: =C37+6 -> 46029 | E37: Customer Collections | F37: International Revenue | G37: GBP | H37: 1940000 | I37: =IFERROR(_xlfn.XLOOKUP(G37,FX_Rates!$C$11:$C$22,FX_Rates!$E$11:$E$22),1) -> 0.792 | J37: =H37*I37 -> 1536480
A38: x | B38: 5 | C38: =Global_Assumptions!$C$8+((B38-1)*7) -> 46030 | D38: =C38+6 -> 46036 | E38: Customer Collections | F38: Recurring Revenue | G38: USD | H38: 14850000 | I38: =IFERROR(_xlfn.XLOOKUP(G38,FX_Rates!$C$11:$C$22,FX_Rates!$E$11:$E$22),1) -> 1 | J38: =H38*I38 -> 14850000
B39: 5 | C39: =Global_Assumptions!$C$8+((B39-1)*7) -> 46030 | D39: =C39+6 -> 46036 | E39: Customer Collections | F39: One-time Payments | G39: USD | H39: 2970000 | I39: =IFERROR(_xlfn.XLOOKUP(G39,FX_Rates!$C$11:$C$22,FX_Rates!$E$11:$E$22),1) -> 1 | J39: =H39*I39 -> 2970000
B40: 5 | C40: =Global_Assumptions!$C$8+((B40-1)*7) -> 46030 | D40: =C40+6 -> 46036 | E40: Settlement Inflows | F40: Merchant Settlements | G40: USD | H40: 24750000 | I40: =IFERROR(_xlfn.XLOOKUP(G40,FX_Rates!$C$11:$C$22,FX_Rates!$E$11:$E$22),1) -> 1 | J40: =H40*I40 -> 24750000
B41: 5 | C41: =Global_Assumptions!$C$8+((B41-1)*7) -> 46030 | D41: =C41+6 -> 46036 | E41: Settlement Inflows | F41: Partner Settlements | G41: EUR | H41: 4950000 | I41: =IFERROR(_xlfn.XLOOKUP(G41,FX_Rates!$C$11:$C$22,FX_Rates!$E$11:$E$22),1) -> 0.948 | J41: =H41*I41 -> 4692600
B42: 5 | C42: =Global_Assumptions!$C$8+((B42-1)*7) -> 46030 | D42: =C42+6 -> 46036 | E42: Interest Income | F42: Money Market | G42: USD | H42: 148500 | I42: =IFERROR(_xlfn.XLOOKUP(G42,FX_Rates!$C$11:$C$22,FX_Rates!$E$11:$E$22),1) -> 1 | J42: =H42*I42 -> 148500
B43: 5 | C43: =Global_Assumptions!$C$8+((B43-1)*7) -> 46030 | D43: =C43+6 -> 46036 | E43: Other Inflows | F43: Tax Refunds | G43: USD | H43: 495000 | I43: =IFERROR(_xlfn.XLOOKUP(G43,FX_Rates!$C$11:$C$22,FX_Rates!$E$11:$E$22),1) -> 1 | J43: =H43*I43 -> 495000
B44: 5 | C44: =Global_Assumptions!$C$8+((B44-1)*7) -> 46030 | D44: =C44+6 -> 46036 | E44: Customer Collections | F44: International Revenue | G44: GBP | H44: 1980000 | I44: =IFERROR(_xlfn.XLOOKUP(G44,FX_Rates!$C$11:$C$22,FX_Rates!$E$11:$E$22),1) -> 0.792 | J44: =H44*I44 -> 1568160
A45: x | B45: 6 | C45: =Global_Assumptions!$C$8+((B45-1)*7) -> 46037 | D45: =C45+6 -> 46043 | E45: Customer Collections | F45: Recurring Revenue | G45: USD | H45: 15150000 | I45: =IFERROR(_xlfn.XLOOKUP(G45,FX_Rates!$C$11:$C$22,FX_Rates!$E$11:$E$22),1) -> 1 | J45: =H45*I45 -> 15150000
B46: 6 | C46: =Global_Assumptions!$C$8+((B46-1)*7) -> 46037 | D46: =C46+6 -> 46043 | E46: Customer Collections | F46: One-time Payments | G46: USD | H46: 3030000 | I46: =IFERROR(_xlfn.XLOOKUP(G46,FX_Rates!$C$11:$C$22,FX_Rates!$E$11:$E$22),1) -> 1 | J46: =H46*I46 -> 3030000
B47: 6 | C47: =Global_Assumptions!$C$8+((B47-1)*7) -> 46037 | D47: =C47+6 -> 46043 | E47: Settlement Inflows | F47: Merchant Settlements | G47: USD | H47: 25250000 | I47: =IFERROR(_xlfn.XLOOKUP(G47,FX_Rates!$C$11:$C$22,FX_Rates!$E$11:$E$22),1) -> 1 | J47: =H47*I47 -> 25250000
B48: 6 | C48: =Global_Assumptions!$C$8+((B48-1)*7) -> 46037 | D48: =C48+6 -> 46043 | E48: Settlement Inflows | F48: Partner Settlements | G48: EUR | H48: 5050000 | I48: =IFERROR(_xlfn.XLOOKUP(G48,FX_Rates!$C$11:$C$22,FX_Rates!$E$11:$E$22),1) -> 0.948 | J48: =H48*I48 -> 4787400
B49: 6 | C49: =Global_Assumptions!$C$8+((B49-1)*7) -> 46037 | D49: =C49+6 -> 46043 | E49: Interest Income | F49: Money Market | G49: USD | H49: 151500 | I49: =IFERROR(_xlfn.XLOOKUP(G49,FX_Rates!$C$11:$C$22,FX_Rates!$E$11:$E$22),1) -> 1 | J49: =H49*I49 -> 151500
B50: 6 | C50: =Global_Assumptions!$C$8+((B50-1)*7) -> 46037 | D50: =C50+6 -> 46043 | E50: Other Inflows | F50: Tax Refunds | G50: USD | H50: 505000 | I50: =IFERROR(_xlfn.XLOOKUP(G50,FX_Rates!$C$11:$C$22,FX_Rates!$E$11:$E$22),1) -> 1 | J50: =H50*I50 -> 505000
B51: 6 | C51: =Global_Assumptions!$C$8+((B51-1)*7) -> 46037 | D51: =C51+6 -> 46043 | E51: Customer Collections | F51: International Revenue | G51: GBP | H51: 2020000 | I51: =IFERROR(_xlfn.XLOOKUP(G51,FX_Rates!$C$11:$C$22,FX_Rates!$E$11:$E$22),1) -> 0.792 | J51: =H51*I51 -> 1599840
A52: x | B52: 7 | C52: =Global_Assumptions!$C$8+((B52-1)*7) -> 46044 | D52: =C52+6 -> 46050 | E52: Customer Collections | F52: Recurring Revenue | G52: USD | H52: 15450000 | I52: =IFERROR(_xlfn.XLOOKUP(G52,FX_Rates!$C$11:$C$22,FX_Rates!$E$11:$E$22),1) -> 1 | J52: =H52*I52 -> 15450000
B53: 7 | C53: =Global_Assumptions!$C$8+((B53-1)*7) -> 46044 | D53: =C53+6 -> 46050 | E53: Customer Collections | F53: One-time Payments | G53: USD | H53: 3090000 | I53: =IFERROR(_xlfn.XLOOKUP(G53,FX_Rates!$C$11:$C$22,FX_Rates!$E$11:$E$22),1) -> 1 | J53: =H53*I53 -> 3090000
B54: 7 | C54: =Global_Assumptions!$C$8+((B54-1)*7) -> 46044 | D54: =C54+6 -> 46050 | E54: Settlement Inflows | F54: Merchant Settlements | G54: USD | H54: 25750000 | I54: =IFERROR(_xlfn.XLOOKUP(G54,FX_Rates!$C$11:$C$22,FX_Rates!$E$11:$E$22),1) -> 1 | J54: =H54*I54 -> 25750000
B55: 7 | C55: =Global_Assumptions!$C$8+((B55-1)*7) -> 46044 | D55: =C55+6 -> 46050 | E55: Settlement Inflows | F55: Partner Settlements | G55: EUR | H55: 5150000 | I55: =IFERROR(_xlfn.XLOOKUP(G55,FX_Rates!$C$11:$C$22,FX_Rates!$E$11:$E$22),1) -> 0.948 | J55: =H55*I55 -> 4882200
B56: 7 | C56: =Global_Assumptions!$C$8+((B56-1)*7) -> 46044 | D56: =C56+6 -> 46050 | E56: Interest Income | F56: Money Market | G56: USD | H56: 154500 | I56: =IFERROR(_xlfn.XLOOKUP(G56,FX_Rates!$C$11:$C$22,FX_Rates!$E$11:$E$22),1) -> 1 | J56: =H56*I56 -> 154500
B57: 7 | C57: =Global_Assumptions!$C$8+((B57-1)*7) -> 46044 | D57: =C57+6 -> 46050 | E57: Other Inflows | F57: Tax Refunds | G57: USD | H57: 515000 | I57: =IFERROR(_xlfn.XLOOKUP(G57,FX_Rates!$C$11:$C$22,FX_Rates!$E$11:$E$22),1) -> 1 | J57: =H57*I57 -> 515000
B58: 7 | C58: =Global_Assumptions!$C$8+((B58-1)*7) -> 46044 | D58: =C58+6 -> 46050 | E58: Customer Collections | F58: International Revenue | G58: GBP | H58: 2060000 | I58: =IFERROR(_xlfn.XLOOKUP(G58,FX_Rates!$C$11:$C$22,FX_Rates!$E$11:$E$22),1) -> 0.792 | J58: =H58*I58 -> 1631520
A59: x | B59: 8 | C59: =Global_Assumptions!$C$8+((B59-1)*7) -> 46051 | D59: =C59+6 -> 46057 | E59: Customer Collections | F59: Recurring Revenue | G59: USD | H59: 14550000 | I59: =IFERROR(_xlfn.XLOOKUP(G59,FX_Rates!$C$11:$C$22,FX_Rates!$E$11:$E$22),1) -> 1 | J59: =H59*I59 -> 14550000
B60: 8 | C60: =Global_Assumptions!$C$8+((B60-1)*7) -> 46051 | D60: =C60+6 -> 46057 | E60: Customer Collections | F60: One-time Payments | G60: USD | H60: 2910000 | I60: =IFERROR(_xlfn.XLOOKUP(G60,FX_Rates!$C$11:$C$22,FX_Rates!$E$11:$E$22),1) -> 1 | J60: =H60*I60 -> 2910000
B61: 8 | C61: =Global_Assumptions!$C$8+((B61-1)*7) -> 46051 | D61: =C61+6 -> 46057 | E61: Settlement Inflows | F61: Merchant Settlements | G61: USD | H61: 24250000 | I61: =IFERROR(_xlfn.XLOOKUP(G61,FX_Rates!$C$11:$C$22,FX_Rates!$E$11:$E$22),1) -> 1 | J61: =H61*I61 -> 24250000
B62: 8 | C62: =Global_Assumptions!$C$8+((B62-1)*7) -> 46051 | D62: =C62+6 -> 46057 | E62: Settlement Inflows | F62: Partner Settlements | G62: EUR | H62: 4850000 | I62: =IFERROR(_xlfn.XLOOKUP(G62,FX_Rates!$C$11:$C$22,FX_Rates!$E$11:$E$22),1) -> 0.948 | J62: =H62*I62 -> 4597800
B63: 8 | C63: =Global_Assumptions!$C$8+((B63-1)*7) -> 46051 | D63: =C63+6 -> 46057 | E63: Interest Income | F63: Money Market | G63: USD | H63: 145500 | I63: =IFERROR(_xlfn.XLOOKUP(G63,FX_Rates!$C$11:$C$22,FX_Rates!$E$11:$E$22),1) -> 1 | J63: =H63*I63 -> 145500
B64: 8 | C64: =Global_Assumptions!$C$8+((B64-1)*7) -> 46051 | D64: =C64+6 -> 46057 | E64: Other Inflows | F64: Tax Refunds | G64: USD | H64: 485000 | I64: =IFERROR(_xlfn.XLOOKUP(G64,FX_Rates!$C$11:$C$22,FX_Rates!$E$11:$E$22),1) -> 1 | J64: =H64*I64 -> 485000
B65: 8 | C65: =Global_Assumptions!$C$8+((B65-1)*7) -> 46051 | D65: =C65+6 -> 46057 | E65: Customer Collections | F65: International Revenue | G65: GBP | H65: 1940000 | I65: =IFERROR(_xlfn.XLOOKUP(G65,FX_Rates!$C$11:$C$22,FX_Rates!$E$11:$E$22),1) -> 0.792 | J65: =H65*I65 -> 1536480
A66: x | B66: 9 | C66: =Global_Assumptions!$C$8+((B66-1)*7) -> 46058 | D66: =C66+6 -> 46064 | E66: Customer Collections | F66: Recurring Revenue | G66: USD | H66: 14850000 | I66: =IFERROR(_xlfn.XLOOKUP(G66,FX_Rates!$C$11:$C$22,FX_Rates!$E$11:$E$22),1) -> 1 | J66: =H66*I66 -> 14850000
B67: 9 | C67: =Global_Assumptions!$C$8+((B67-1)*7) -> 46058 | D67: =C67+6 -> 46064 | E67: Customer Collections | F67: One-time Payments | G67: USD | H67: 2970000 | I67: =IFERROR(_xlfn.XLOOKUP(G67,FX_Rates!$C$11:$C$22,FX_Rates!$E$11:$E$22),1) -> 1 | J67: =H67*I67 -> 2970000
B68: 9 | C68: =Global_Assumptions!$C$8+((B68-1)*7) -> 46058 | D68: =C68+6 -> 46064 | E68: Settlement Inflows | F68: Merchant Settlements | G68: USD | H68: 24750000 | I68: =IFERROR(_xlfn.XLOOKUP(G68,FX_Rates!$C$11:$C$22,FX_Rates!$E$11:$E$22),1) -> 1 | J68: =H68*I68 -> 24750000
B69: 9 | C69: =Global_Assumptions!$C$8+((B69-1)*7) -> 46058 | D69: =C69+6 -> 46064 | E69: Settlement Inflows | F69: Partner Settlements | G69: EUR | H69: 4950000 | I69: =IFERROR(_xlfn.XLOOKUP(G69,FX_Rates!$C$11:$C$22,FX_Rates!$E$11:$E$22),1) -> 0.948 | J69: =H69*I69 -> 4692600
B70: 9 | C70: =Global_Assumptions!$C$8+((B70-1)*7) -> 46058 | D70: =C70+6 -> 46064 | E70: Interest Income | F70: Money Market | G70: USD | H70: 148500 | I70: =IFERROR(_xlfn.XLOOKUP(G70,FX_Rates!$C$11:$C$22,FX_Rates!$E$11:$E$22),1) -> 1 | J70: =H70*I70 -> 148500
B71: 9 | C71: =Global_Assumptions!$C$8+((B71-1)*7) -> 46058 | D71: =C71+6 -> 46064 | E71: Other Inflows | F71: Tax Refunds | G71: USD | H71: 495000 | I71: =IFERROR(_xlfn.XLOOKUP(G71,FX_Rates!$C$11:$C$22,FX_Rates!$E$11:$E$22),1) -> 1 | J71: =H71*I71 -> 495000
B72: 9 | C72: =Global_Assumptions!$C$8+((B72-1)*7) -> 46058 | D72: =C72+6 -> 46064 | E72: Customer Collections | F72: International Revenue | G72: GBP | H72: 1980000 | I72: =IFERROR(_xlfn.XLOOKUP(G72,FX_Rates!$C$11:$C$22,FX_Rates!$E$11:$E$22),1) -> 0.792 | J72: =H72*I72 -> 1568160
A73: x | B73: 10 | C73: =Global_Assumptions!$C$8+((B73-1)*7) -> 46065 | D73: =C73+6 -> 46071 | E73: Customer Collections | F73: Recurring Revenue | G73: USD | H73: 15150000 | I73: =IFERROR(_xlfn.XLOOKUP(G73,FX_Rates!$C$11:$C$22,FX_Rates!$E$11:$E$22),1) -> 1 | J73: =H73*I73 -> 15150000
B74: 10 | C74: =Global_Assumptions!$C$8+((B74-1)*7) -> 46065 | D74: =C74+6 -> 46071 | E74: Customer Collections | F74: One-time Payments | G74: USD | H74: 3030000 | I74: =IFERROR(_xlfn.XLOOKUP(G74,FX_Rates!$C$11:$C$22,FX_Rates!$E$11:$E$22),1) -> 1 | J74: =H74*I74 -> 3030000
B75: 10 | C75: =Global_Assumptions!$C$8+((B75-1)*7) -> 46065 | D75: =C75+6 -> 46071 | E75: Settlement Inflows | F75: Merchant Settlements | G75: USD | H75: 25250000 | I75: =IFERROR(_xlfn.XLOOKUP(G75,FX_Rates!$C$11:$C$22,FX_Rates!$E$11:$E$22),1) -> 1 | J75: =H75*I75 -> 25250000
B76: 10 | C76: =Global_Assumptions!$C$8+((B76-1)*7) -> 46065 | D76: =C76+6 -> 46071 | E76: Settlement Inflows | F76: Partner Settlements | G76: EUR | H76: 5050000 | I76: =IFERROR(_xlfn.XLOOKUP(G76,FX_Rates!$C$11:$C$22,FX_Rates!$E$11:$E$22),1) -> 0.948 | J76: =H76*I76 -> 4787400
B77: 10 | C77: =Global_Assumptions!$C$8+((B77-1)*7) -> 46065 | D77: =C77+6 -> 46071 | E77: Interest Income | F77: Money Market | G77: USD | H77: 151500 | I77: =IFERROR(_xlfn.XLOOKUP(G77,FX_Rates!$C$11:$C$22,FX_Rates!$E$11:$E$22),1) -> 1 | J77: =H77*I77 -> 151500
B78: 10 | C78: =Global_Assumptions!$C$8+((B78-1)*7) -> 46065 | D78: =C78+6 -> 46071 | E78: Other Inflows | F78: Tax Refunds | G78: USD | H78: 505000 | I78: =IFERROR(_xlfn.XLOOKUP(G78,FX_Rates!$C$11:$C$22,FX_Rates!$E$11:$E$22),1) -> 1 | J78: =H78*I78 -> 505000
B79: 10 | C79: =Global_Assumptions!$C$8+((B79-1)*7) -> 46065 | D79: =C79+6 -> 46071 | E79: Customer Collections | F79: International Revenue | G79: GBP | H79: 2020000 | I79: =IFERROR(_xlfn.XLOOKUP(G79,FX_Rates!$C$11:$C$22,FX_Rates!$E$11:$E$22),1) -> 0.792 | J79: =H79*I79 -> 1599840
A80: x | B80: 11 | C80: =Global_Assumptions!$C$8+((B80-1)*7) -> 46072 | D80: =C80+6 -> 46078 | E80: Customer Collections | F80: Recurring Revenue | G80: USD | H80: 15450000 | I80: =IFERROR(_xlfn.XLOOKUP(G80,FX_Rates!$C$11:$C$22,FX_Rates!$E$11:$E$22),1) -> 1 | J80: =H80*I80 -> 15450000
B81: 11 | C81: =Global_Assumptions!$C$8+((B81-1)*7) -> 46072 | D81: =C81+6 -> 46078 | E81: Customer Collections | F81: One-time Payments | G81: USD | H81: 3090000 | I81: =IFERROR(_xlfn.XLOOKUP(G81,FX_Rates!$C$11:$C$22,FX_Rates!$E$11:$E$22),1) -> 1 | J81: =H81*I81 -> 3090000
B82: 11 | C82: =Global_Assumptions!$C$8+((B82-1)*7) -> 46072 | D82: =C82+6 -> 46078 | E82: Settlement Inflows | F82: Merchant Settlements | G82: USD | H82: 25750000 | I82: =IFERROR(_xlfn.XLOOKUP(G82,FX_Rates!$C$11:$C$22,FX_Rates!$E$11:$E$22),1) -> 1 | J82: =H82*I82 -> 25750000
B83: 11 | C83: =Global_Assumptions!$C$8+((B83-1)*7) -> 46072 | D83: =C83+6 -> 46078 | E83: Settlement Inflows | F83: Partner Settlements | G83: EUR | H83: 5150000 | I83: =IFERROR(_xlfn.XLOOKUP(G83,FX_Rates!$C$11:$C$22,FX_Rates!$E$11:$E$22),1) -> 0.948 | J83: =H83*I83 -> 4882200
B84: 11 | C84: =Global_Assumptions!$C$8+((B84-1)*7) -> 46072 | D84: =C84+6 -> 46078 | E84: Interest Income | F84: Money Market | G84: USD | H84: 154500 | I84: =IFERROR(_xlfn.XLOOKUP(G84,FX_Rates!$C$11:$C$22,FX_Rates!$E$11:$E$22),1) -> 1 | J84: =H84*I84 -> 154500
B85: 11 | C85: =Global_Assumptions!$C$8+((B85-1)*7) -> 46072 | D85: =C85+6 -> 46078 | E85: Other Inflows | F85: Tax Refunds | G85: USD | H85: 515000 | I85: =IFERROR(_xlfn.XLOOKUP(G85,FX_Rates!$C$11:$C$22,FX_Rates!$E$11:$E$22),1) -> 1 | J85: =H85*I85 -> 515000
B86: 11 | C86: =Global_Assumptions!$C$8+((B86-1)*7) -> 46072 | D86: =C86+6 -> 46078 | E86: Customer Collections | F86: International Revenue | G86: GBP | H86: 2060000 | I86: =IFERROR(_xlfn.XLOOKUP(G86,FX_Rates!$C$11:$C$22,FX_Rates!$E$11:$E$22),1) -> 0.792 | J86: =H86*I86 -> 1631520
A87: x | B87: 12 | C87: =Global_Assumptions!$C$8+((B87-1)*7) -> 46079 | D87: =C87+6 -> 46085 | E87: Customer Collections | F87: Recurring Revenue | G87: USD | H87: 14550000 | I87: =IFERROR(_xlfn.XLOOKUP(G87,FX_Rates!$C$11:$C$22,FX_Rates!$E$11:$E$22),1) -> 1 | J87: =H87*I87 -> 14550000
B88: 12 | C88: =Global_Assumptions!$C$8+((B88-1)*7) -> 46079 | D88: =C88+6 -> 46085 | E88: Customer Collections | F88: One-time Payments | G88: USD | H88: 2910000 | I88: =IFERROR(_xlfn.XLOOKUP(G88,FX_Rates!$C$11:$C$22,FX_Rates!$E$11:$E$22),1) -> 1 | J88: =H88*I88 -> 2910000
B89: 12 | C89: =Global_Assumptions!$C$8+((B89-1)*7) -> 46079 | D89: =C89+6 -> 46085 | E89: Settlement Inflows | F89: Merchant Settlements | G89: USD | H89: 24250000 | I89: =IFERROR(_xlfn.XLOOKUP(G89,FX_Rates!$C$11:$C$22,FX_Rates!$E$11:$E$22),1) -> 1 | J89: =H89*I89 -> 24250000
B90: 12 | C90: =Global_Assumptions!$C$8+((B90-1)*7) -> 46079 | D90: =C90+6 -> 46085 | E90: Settlement Inflows | F90: Partner Settlements | G90: EUR | H90: 4850000 | I90: =IFERROR(_xlfn.XLOOKUP(G90,FX_Rates!$C$11:$C$22,FX_Rates!$E$11:$E$22),1) -> 0.948 | J90: =H90*I90 -> 4597800
B91: 12 | C91: =Global_Assumptions!$C$8+((B91-1)*7) -> 46079 | D91: =C91+6 -> 46085 | E91: Interest Income | F91: Money Market | G91: USD | H91: 145500 | I91: =IFERROR(_xlfn.XLOOKUP(G91,FX_Rates!$C$11:$C$22,FX_Rates!$E$11:$E$22),1) -> 1 | J91: =H91*I91 -> 145500
B92: 12 | C92: =Global_Assumptions!$C$8+((B92-1)*7) -> 46079 | D92: =C92+6 -> 46085 | E92: Other Inflows | F92: Tax Refunds | G92: USD | H92: 485000 | I92: =IFERROR(_xlfn.XLOOKUP(G92,FX_Rates!$C$11:$C$22,FX_Rates!$E$11:$E$22),1) -> 1 | J92: =H92*I92 -> 485000
B93: 12 | C93: =Global_Assumptions!$C$8+((B93-1)*7) -> 46079 | D93: =C93+6 -> 46085 | E93: Customer Collections | F93: International Revenue | G93: GBP | H93: 1940000 | I93: =IFERROR(_xlfn.XLOOKUP(G93,FX_Rates!$C$11:$C$22,FX_Rates!$E$11:$E$22),1) -> 0.792 | J93: =H93*I93 -> 1536480
A94: x | B94: 13 | C94: =Global_Assumptions!$C$8+((B94-1)*7) -> 46086 | D94: =C94+6 -> 46092 | E94: Customer Collections | F94: Recurring Revenue | G94: USD | H94: 14850000 | I94: =IFERROR(_xlfn.XLOOKUP(G94,FX_Rates!$C$11:$C$22,FX_Rates!$E$11:$E$22),1) -> 1 | J94: =H94*I94 -> 14850000
B95: 13 | C95: =Global_Assumptions!$C$8+((B95-1)*7) -> 46086 | D95: =C95+6 -> 46092 | E95: Customer Collections | F95: One-time Payments | G95: USD | H95: 2970000 | I95: =IFERROR(_xlfn.XLOOKUP(G95,FX_Rates!$C$11:$C$22,FX_Rates!$E$11:$E$22),1) -> 1 | J95: =H95*I95 -> 2970000
B96: 13 | C96: =Global_Assumptions!$C$8+((B96-1)*7) -> 46086 | D96: =C96+6 -> 46092 | E96: Settlement Inflows | F96: Merchant Settlements | G96: USD | H96: 24750000 | I96: =IFERROR(_xlfn.XLOOKUP(G96,FX_Rates!$C$11:$C$22,FX_Rates!$E$11:$E$22),1) -> 1 | J96: =H96*I96 -> 24750000
B97: 13 | C97: =Global_Assumptions!$C$8+((B97-1)*7) -> 46086 | D97: =C97+6 -> 46092 | E97: Settlement Inflows | F97: Partner Settlements | G97: EUR | H97: 4950000 | I97: =IFERROR(_xlfn.XLOOKUP(G97,FX_Rates!$C$11:$C$22,FX_Rates!$E$11:$E$22),1) -> 0.948 | J97: =H97*I97 -> 4692600
B98: 13 | C98: =Global_Assumptions!$C$8+((B98-1)*7) -> 46086 | D98: =C98+6 -> 46092 | E98: Interest Income | F98: Money Market | G98: USD | H98: 148500 | I98: =IFERROR(_xlfn.XLOOKUP(G98,FX_Rates!$C$11:$C$22,FX_Rates!$E$11:$E$22),1) -> 1 | J98: =H98*I98 -> 148500
B99: 13 | C99: =Global_Assumptions!$C$8+((B99-1)*7) -> 46086 | D99: =C99+6 -> 46092 | E99: Other Inflows | F99: Tax Refunds | G99: USD | H99: 495000 | I99: =IFERROR(_xlfn.XLOOKUP(G99,FX_Rates!$C$11:$C$22,FX_Rates!$E$11:$E$22),1) -> 1 | J99: =H99*I99 -> 495000
A100: x | B100: 13 | C100: =Global_Assumptions!$C$8+((B100-1)*7) -> 46086 | D100: =C100+6 -> 46092 | E100: Customer Collections | F100: International Revenue | G100: GBP | H100: 1980000 | I100: =IFERROR(_xlfn.XLOOKUP(G100,FX_Rates!$C$11:$C$22,FX_Rates!$E$11:$E$22),1) -> 0.792 | J100: =H100*I100 -> 1568160

Sheet Cash_Outflows
B2: CASH OUTFLOWS (FORECAST)
B3: Data connected via SQL / POWER QUERY
B5: Data Source: | D5: [FP&A Forecast System / AP System]
B6: Refresh Frequency: | D6: Weekly (Monday)
B7: Last Refresh: | D7: [AUTO-TIMESTAMP]
B9: Week # | C9: Week Start Date | D9: Week End Date | E9: Category | F9: Sub-Category | G9: Currency | H9: Amount (USD) | I9: FX Rate | J9: Amount (USD) | K9: Scenario Multiplier
A10: x | B10: 1 | C10: =Global_Assumptions!$C$8+((B10-1)*7) -> 46002 | D10: =C10+6 -> 46008 | E10: Settlements | F10: Merchant Payouts | G10: USD | H10: 20000000 | I10: =IFERROR(_xlfn.XLOOKUP(G10,FX_Rates!$C$11:$C$22,FX_Rates!$E$11:$E$22),1) -> 1 | J10: =H10*I10*K10 -> 20000000 | K10: 1
B11: 1 | C11: =Global_Assumptions!$C$8+((B11-1)*7) -> 46002 | D11: =C11+6 -> 46008 | E11: Settlements | F11: Partner Payments | G11: USD | H11: 8000000 | I11: =IFERROR(_xlfn.XLOOKUP(G11,FX_Rates!$C$11:$C$22,FX_Rates!$E$11:$E$22),1) -> 1 | J11: =H11*I11*K11 -> 8000000 | K11: 1 | N11: SUMMARY BY WEEK
B12: 1 | C12: =Global_Assumptions!$C$8+((B12-1)*7) -> 46002 | D12: =C12+6 -> 46008 | E12: Settlements | F12: International Payouts | G12: EUR | H12: 3000000 | I12: =IFERROR(_xlfn.XLOOKUP(G12,FX_Rates!$C$11:$C$22,FX_Rates!$E$11:$E$22),1) -> 0.948 | J12: =H12*I12*K12 -> 2844000 | K12: 1 | N12: Week | O12: Total Outflows (USD)
B13: 1 | C13: =Global_Assumptions!$C$8+((B13-1)*7) -> 46002 | D13: =C13+6 -> 46008 | E13: Operating Expenses | F13: Technology & Infrastructure | G13: USD | H13: 2500000 | I13: =IFERROR(_xlfn.XLOOKUP(G13,FX_Rates!$C$11:$C$22,FX_Rates!$E$11:$E$22),1) -> 1 | J13: =H13*I13*K13 -> 2500000 | K13: 1 | N13: 1 | O13: =SUMIF($B$10:$B$139,N13,$J$10:$J$139) -> 42977600
B14: 1 | C14: =Global_Assumptions!$C$8+((B14-1)*7) -> 46002 | D14: =C14+6 -> 46008 | E14: Operating Expenses | F14: Marketing | G14: USD | H14: 1500000 | I14: =IFERROR(_xlfn.XLOOKUP(G14,FX_Rates!$C$11:$C$22,FX_Rates!$E$11:$E$22),1) -> 1 | J14: =H14*I14*K14 -> 1500000 | K14: 1 | N14: 2 | O14: =SUMIF($B$10:$B$139,N14,$J$10:$J$139) -> 50676920
B15: 1 | C15: =Global_Assumptions!$C$8+((B15-1)*7) -> 46002 | D15: =C15+6 -> 46008 | E15: Operating Expenses | F15: G&A | G15: USD | H15: 1000000 | I15: =IFERROR(_xlfn.XLOOKUP(G15,FX_Rates!$C$11:$C$22,FX_Rates!$E$11:$E$22),1) -> 1 | J15: =H15*I15*K15 -> 1000000 | K15: 1 | N15: 3 | O15: =SUMIF($B$10:$B$139,N15,$J$10:$J$139) -> 42332936
B16: 1 | C16: =Global_Assumptions!$C$8+((B16-1)*7) -> 46002 | D16: =C16+6 -> 46008 | E16: Payroll | F16: US Payroll | G16: USD | H16: 4000000 | I16: =IFERROR(_xlfn.XLOOKUP(G16,FX_Rates!$C$11:$C$22,FX_Rates!$E$11:$E$22),1) -> 1 | J16: =H16*I16*K16 -> 4000000 | K16: 1 | N16: 4 | O16: =SUMIF($B$10:$B$139,N16,$J$10:$J$139) -> 53928000
B17: 1 | C17: =Global_Assumptions!$C$8+((B17-1)*7) -> 46002 | D17: =C17+6 -> 46008 | E17: Payroll | F17: International Payroll | G17: GBP | H17: 800000 | I17: =IFERROR(_xlfn.XLOOKUP(G17,FX_Rates!$C$11:$C$22,FX_Rates!$E$11:$E$22),1) -> 0.792 | J17: =H17*I17*K17 -> 633600 | K17: 1 | N17: 5 | O17: =SUMIF($B$10:$B$139,N17,$J$10:$J$139) -> 43622264
B18: 1 | C18: =Global_Assumptions!$C$8+((B18-1)*7) -> 46002 | D18: =C18+6 -> 46008 | E18: Taxes | F18: Income Tax | G18: USD | H18: 2000000 | I18: =IFERROR(_xlfn.XLOOKUP(G18,FX_Rates!$C$11:$C$22,FX_Rates!$E$11:$E$22),1) -> 1 | J18: =H18*I18*K18 -> 2000000 | K18: 1 | N18: 6 | O18: =SUMIF($B$10:$B$139,N18,$J$10:$J$139) -> 49179080
B19: 1 | C19: =Global_Assumptions!$C$8+((B19-1)*7) -> 46002 | D19: =C19+6 -> 46008 | E19: Debt Service | F19: Interest Payments | G19: USD | H19: 500000 | I19: =IFERROR(_xlfn.XLOOKUP(G19,FX_Rates!$C$11:$C$22,FX_Rates!$E$11:$E$22),1) -> 1 | J19: =H19*I19*K19 -> 500000 | K19: 1 | N19: 7 | O19: =SUMIF($B$10:$B$139,N19,$J$10:$J$139) -> 42977600
A20: x | B20: 2 | C20: =Global_Assumptions!$C$8+((B20-1)*7) -> 46009 | D20: =C20+6 -> 46015 | E20: Settlements | F20: Merchant Payouts | G20: USD | H20: 20300000 | I20: =IFERROR(_xlfn.XLOOKUP(G20,FX_Rates!$C$11:$C$22,FX_Rates!$E$11:$E$22),1) -> 1 | J20: =H20*I20*K20 -> 20300000 | K20: 1 | N20: 8 | O20: =SUMIF($B$10:$B$139,N20,$J$10:$J$139) -> 50676920
B21: 2 | C21: =Global_Assumptions!$C$8+((B21-1)*7) -> 46009 | D21: =C21+6 -> 46015 | E21: Settlements | F21: Partner Payments | G21: USD | H21: 8120000 | I21: =IFERROR(_xlfn.XLOOKUP(G21,FX_Rates!$C$11:$C$22,FX_Rates!$E$11:$E$22),1) -> 1 | J21: =H21*I21*K21 -> 8120000 | K21: 1 | N21: 9 | O21: =SUMIF($B$10:$B$139,N21,$J$10:$J$139) -> 42332936
B22: 2 | C22: =Global_Assumptions!$C$8+((B22-1)*7) -> 46009 | D22: =C22+6 -> 46015 | E22: Settlements | F22: International Payouts | G22: EUR | H22: 3045000 | I22: =IFERROR(_xlfn.XLOOKUP(G22,FX_Rates!$C$11:$C$22,FX_Rates!$E$11:$E$22),1) -> 0.948 | J22: =H22*I22*K22 -> 2886660 | K22: 1 | N22: 10 | O22: =SUMIF($B$10:$B$139,N22,$J$10:$J$139) -> 49928000
B23: 2 | C23: =Global_Assumptions!$C$8+((B23-1)*7) -> 46009 | D23: =C23+6 -> 46015 | E23: Operating Expenses | F23: Technology & Infrastructure | G23: USD | H23: 2537500 | I23: =IFERROR(_xlfn.XLOOKUP(G23,FX_Rates!$C$11:$C$22,FX_Rates!$E$11:$E$22),1) -> 1 | J23: =H23*I23*K23 -> 2537500 | K23: 1 | N23: 11 | O23: =SUMIF($B$10:$B$139,N23,$J$10:$J$139) -> 43622264
B24: 2 | C24: =Global_Assumptions!$C$8+((B24-1)*7) -> 46009 | D24: =C24+6 -> 46015 | E24: Operating Expenses | F24: Marketing | G24: USD | H24: 1522500 | I24: =IFERROR(_xlfn.XLOOKUP(G24,FX_Rates!$C$11:$C$22,FX_Rates!$E$11:$E$22),1) -> 1 | J24: =H24*I24*K24 -> 1522500 | K24: 1 | N24: 12 | O24: =SUMIF($B$10:$B$139,N24,$J$10:$J$139) -> 49179080
B25: 2 | C25: =Global_Assumptions!$C$8+((B25-1)*7) -> 46009 | D25: =C25+6 -> 46015 | E25: Operating Expenses | F25: G&A | G25: USD | H25: 1015000 | I25: =IFERROR(_xlfn.XLOOKUP(G25,FX_Rates!$C$11:$C$22,FX_Rates!$E$11:$E$22),1) -> 1 | J25: =H25*I25*K25 -> 1015000 | K25: 1 | N25: 13 | O25: =SUMIF($B$10:$B$139,N25,$J$10:$J$139) -> 42977600
B26: 2 | C26: =Global_Assumptions!$C$8+((B26-1)*7) -> 46009 | D26: =C26+6 -> 46015 | E26: Payroll | F26: US Payroll | G26: USD | H26: 10150000 | I26: =IFERROR(_xlfn.XLOOKUP(G26,FX_Rates!$C$11:$C$22,FX_Rates!$E$11:$E$22),1) -> 1 | J26: =H26*I26*K26 -> 10150000 | K26: 1 | N26: TOTAL | O26: =SUM(O13:O25) -> 604411200
B27: 2 | C27: =Global_Assumptions!$C$8+((B27-1)*7) -> 46009 | D27: =C27+6 -> 46015 | E27: Payroll | F27: International Payroll | G27: GBP | H27: 2030000 | I27: =IFERROR(_xlfn.XLOOKUP(G27,FX_Rates!$C$11:$C$22,FX_Rates!$E$11:$E$22),1) -> 0.792 | J27: =H27*I27*K27 -> 1607760 | K27: 1
B28: 2 | C28: =Global_Assumptions!$C$8+((B28-1)*7) -> 46009 | D28: =C28+6 -> 46015 | E28: Taxes | F28: Income Tax | G28: USD | H28: 2030000 | I28: =IFERROR(_xlfn.XLOOKUP(G28,FX_Rates!$C$11:$C$22,FX_Rates!$E$11:$E$22),1) -> 1 | J28: =H28*I28*K28 -> 2030000 | K28: 1 | N28: SUMMARY BY CATEGORY
B29: 2 | C29: =Global_Assumptions!$C$8+((B29-1)*7) -> 46009 | D29: =C29+6 -> 46015 | E29: Debt Service | F29: Interest Payments | G29: USD | H29: 507500 | I29: =IFERROR(_xlfn.XLOOKUP(G29,FX_Rates!$C$11:$C$22,FX_Rates!$E$11:$E$22),1) -> 1 | J29: =H29*I29*K29 -> 507500 | K29: 1 | N29: Category | O29: Total (USD) | P29: % of Total
A30: x | B30: 3 | C30: =Global_Assumptions!$C$8+((B30-1)*7) -> 46016 | D30: =C30+6 -> 46022 | E30: Settlements | F30: Merchant Payouts | G30: USD | H30: 19700000 | I30: =IFERROR(_xlfn.XLOOKUP(G30,FX_Rates!$C$11:$C$22,FX_Rates!$E$11:$E$22),1) -> 1 | J30: =H30*I30*K30 -> 19700000 | K30: 1 | N30: Settlements | O30: =SUMIF($E$10:$E$139,N30,$J$10:$J$139) -> 400972000 | P30: =O30/$O$35 -> 0.66340928
B31: 3 | C31: =Global_Assumptions!$C$8+((B31-1)*7) -> 46016 | D31: =C31+6 -> 46022 | E31: Settlements | F31: Partner Payments | G31: USD | H31: 7880000 | I31: =IFERROR(_xlfn.XLOOKUP(G31,FX_Rates!$C$11:$C$22,FX_Rates!$E$11:$E$22),1) -> 1 | J31: =H31*I31*K31 -> 7880000 | K31: 1 | N31: Operating Expenses | O31: =SUMIF($E$10:$E$139,N31,$J$10:$J$139) -> 65000000 | P31: =O31/$O$35 -> 0.10754268
B32: 3 | C32: =Global_Assumptions!$C$8+((B32-1)*7) -> 46016 | D32: =C32+6 -> 46022 | E32: Settlements | F32: International Payouts | G32: EUR | H32: 2955000 | I32: =IFERROR(_xlfn.XLOOKUP(G32,FX_Rates!$C$11:$C$22,FX_Rates!$E$11:$E$22),1) -> 0.948 | J32: =H32*I32*K32 -> 2801340 | K32: 1 | N32: Payroll | O32: =SUMIF($E$10:$E$139,N32,$J$10:$J$139) -> 101939200 | P32: =O32/$O$35 -> 0.16865869
B33: 3 | C33: =Global_Assumptions!$C$8+((B33-1)*7) -> 46016 | D33: =C33+6 -> 46022 | E33: Operating Expenses | F33: Technology & Infrastructure | G33: USD | H33: 2462500 | I33: =IFERROR(_xlfn.XLOOKUP(G33,FX_Rates!$C$11:$C$22,FX_Rates!$E$11:$E$22),1) -> 1 | J33: =H33*I33*K33 -> 2462500 | K33: 1 | N33: Taxes | O33: =SUMIF($E$10:$E$139,N33,$J$10:$J$139) -> 30000000 | P33: =O33/$O$35 -> 0.049635083
B34: 3 | C34: =Global_Assumptions!$C$8+((B34-1)*7) -> 46016 | D34: =C34+6 -> 46022 | E34: Operating Expenses | F34: Marketing | G34: USD | H34: 1477500 | I34: =IFERROR(_xlfn.XLOOKUP(G34,FX_Rates!$C$11:$C$22,FX_Rates!$E$11:$E$22),1) -> 1 | J34: =H34*I34*K34 -> 1477500 | K34: 1 | N34: Debt Service | O34: =SUMIF($E$10:$E$139,N34,$J$10:$J$139) -> 6500000 | P34: =O34/$O$35 -> 0.010754268
B35: 3 | C35: =Global_Assumptions!$C$8+((B35-1)*7) -> 46016 | D35: =C35+6 -> 46022 | E35: Operating Expenses | F35: G&A | G35: USD | H35: 985000 | I35: =IFERROR(_xlfn.XLOOKUP(G35,FX_Rates!$C$11:$C$22,FX_Rates!$E$11:$E$22),1) -> 1 | J35: =H35*I35*K35 -> 985000 | K35: 1 | N35: TOTAL | O35: =SUM(O30:O34) -> 604411200 | P35: 1
B36: 3 | C36: =Global_Assumptions!$C$8+((B36-1)*7) -> 46016 | D36: =C36+6 -> 46022 | E36: Payroll | F36: US Payroll | G36: USD | H36: 3940000 | I36: =IFERROR(_xlfn.XLOOKUP(G36,FX_Rates!$C$11:$C$22,FX_Rates!$E$11:$E$22),1) -> 1 | J36: =H36*I36*K36 -> 3940000 | K36: 1
B37: 3 | C37: =Global_Assumptions!$C$8+((B37-1)*7) -> 46016 | D37: =C37+6 -> 46022 | E37: Payroll | F37: International Payroll | G37: GBP | H37: 788000 | I37: =IFERROR(_xlfn.XLOOKUP(G37,FX_Rates!$C$11:$C$22,FX_Rates!$E$11:$E$22),1) -> 0.792 | J37: =H37*I37*K37 -> 624096 | K37: 1 | N37: SCENARIO ANALYSIS
B38: 3 | C38: =Global_Assumptions!$C$8+((B38-1)*7) -> 46016 | D38: =C38+6 -> 46022 | E38: Taxes | F38: Income Tax | G38: USD | H38: 1970000 | I38: =IFERROR(_xlfn.XLOOKUP(G38,FX_Rates!$C$11:$C$22,FX_Rates!$E$11:$E$22),1) -> 1 | J38: =H38*I38*K38 -> 1970000 | K38: 1 | N38: Adjust 'Scenario Multiplier' column (K) to stress test outflows:
B39: 3 | C39: =Global_Assumptions!$C$8+((B39-1)*7) -> 46016 | D39: =C39+6 -> 46022 | E39: Debt Service | F39: Interest Payments | G39: USD | H39: 492500 | I39: =IFERROR(_xlfn.XLOOKUP(G39,FX_Rates!$C$11:$C$22,FX_Rates!$E$11:$E$22),1) -> 1 | J39: =H39*I39*K39 -> 492500 | K39: 1 | N39: 1.00 = Base case | O39: 1.10 = 10% increase | P39: 0.90 = 10% decrease
A40: x | B40: 4 | C40: =Global_Assumptions!$C$8+((B40-1)*7) -> 46023 | D40: =C40+6 -> 46029 | E40: Settlements | F40: Merchant Payouts | G40: USD | H40: 20000000 | I40: =IFERROR(_xlfn.XLOOKUP(G40,FX_Rates!$C$11:$C$22,FX_Rates!$E$11:$E$22),1) -> 1 | J40: =H40*I40*K40 -> 20000000 | K40: 1
B41: 4 | C41: =Global_Assumptions!$C$8+((B41-1)*7) -> 46023 | D41: =C41+6 -> 46029 | E41: Settlements | F41: Partner Payments | G41: USD | H41: 8000000 | I41: =IFERROR(_xlfn.XLOOKUP(G41,FX_Rates!$C$11:$C$22,FX_Rates!$E$11:$E$22),1) -> 1 | J41: =H41*I41*K41 -> 8000000 | K41: 1
B42: 4 | C42: =Global_Assumptions!$C$8+((B42-1)*7) -> 46023 | D42: =C42+6 -> 46029 | E42: Settlements | F42: International Payouts | G42: EUR | H42: 3000000 | I42: =IFERROR(_xlfn.XLOOKUP(G42,FX_Rates!$C$11:$C$22,FX_Rates!$E$11:$E$22),1) -> 0.948 | J42: =H42*I42*K42 -> 2844000 | K42: 1
B43: 4 | C43: =Global_Assumptions!$C$8+((B43-1)*7) -> 46023 | D43: =C43+6 -> 46029 | E43: Operating Expenses | F43: Technology & Infrastructure | G43: USD | H43: 2500000 | I43: =IFERROR(_xlfn.XLOOKUP(G43,FX_Rates!$C$11:$C$22,FX_Rates!$E$11:$E$22),1) -> 1 | J43: =H43*I43*K43 -> 2500000 | K43: 1
B44: 4 | C44: =Global_Assumptions!$C$8+((B44-1)*7) -> 46023 | D44: =C44+6 -> 46029 | E44: Operating Expenses | F44: Marketing | G44: USD | H44: 1500000 | I44: =IFERROR(_xlfn.XLOOKUP(G44,FX_Rates!$C$11:$C$22,FX_Rates!$E$11:$E$22),1) -> 1 | J44: =H44*I44*K44 -> 1500000 | K44: 1
B45: 4 | C45: =Global_Assumptions!$C$8+((B45-1)*7) -> 46023 | D45: =C45+6 -> 46029 | E45: Operating Expenses | F45: G&A | G45: USD | H45: 1000000 | I45: =IFERROR(_xlfn.XLOOKUP(G45,FX_Rates!$C$11:$C$22,FX_Rates!$E$11:$E$22),1) -> 1 | J45: =H45*I45*K45 -> 1000000 | K45: 1
B46: 4 | C46: =Global_Assumptions!$C$8+((B46-1)*7) -> 46023 | D46: =C46+6 -> 46029 | E46: Payroll | F46: US Payroll | G46: USD | H46: 10000000 | I46: =IFERROR(_xlfn.XLOOKUP(G46,FX_Rates!$C$11:$C$22,FX_Rates!$E$11:$E$22),1) -> 1 | J46: =H46*I46*K46 -> 10000000 | K46: 1
B47: 4 | C47: =Global_Assumptions!$C$8+((B47-1)*7) -> 46023 | D47: =C47+6 -> 46029 | E47: Payroll | F47: International Payroll | G47: GBP | H47: 2000000 | I47: =IFERROR(_xlfn.XLOOKUP(G47,FX_Rates!$C$11:$C$22,FX_Rates!$E$11:$E$22),1) -> 0.792 | J47: =H47*I47*K47 -> 1584000 | K47: 1
B48: 4 | C48: =Global_Assumptions!$C$8+((B48-1)*7) -> 46023 | D48: =C48+6 -> 46029 | E48: Taxes | F48: Income Tax | G48: USD | H48: 6000000 | I48: =IFERROR(_xlfn.XLOOKUP(G48,FX_Rates!$C$11:$C$22,FX_Rates!$E$11:$E$22),1) -> 1 | J48: =H48*I48*K48 -> 6000000 | K48: 1
B49: 4 | C49: =Global_Assumptions!$C$8+((B49-1)*7) -> 46023 | D49: =C49+6 -> 46029 | E49: Debt Service | F49: Interest Payments | G49: USD | H49: 500000 | I49: =IFERROR(_xlfn.XLOOKUP(G49,FX_Rates!$C$11:$C$22,FX_Rates!$E$11:$E$22),1) -> 1 | J49: =H49*I49*K49 -> 500000 | K49: 1
A50: x | B50: 5 | C50: =Global_Assumptions!$C$8+((B50-1)*7) -> 46030 | D50: =C50+6 -> 46036 | E50: Settlements | F50: Merchant Payouts | G50: USD | H50: 20300000 | I50: =IFERROR(_xlfn.XLOOKUP(G50,FX_Rates!$C$11:$C$22,FX_Rates!$E$11:$E$22),1) -> 1 | J50: =H50*I50*K50 -> 20300000 | K50: 1
B51: 5 | C51: =Global_Assumptions!$C$8+((B51-1)*7) -> 46030 | D51: =C51+6 -> 46036 | E51: Settlements | F51: Partner Payments | G51: USD | H51: 8120000 | I51: =IFERROR(_xlfn.XLOOKUP(G51,FX_Rates!$C$11:$C$22,FX_Rates!$E$11:$E$22),1) -> 1 | J51: =H51*I51*K51 -> 8120000 | K51: 1
B52: 5 | C52: =Global_Assumptions!$C$8+((B52-1)*7) -> 46030 | D52: =C52+6 -> 46036 | E52: Settlements | F52: International Payouts | G52: EUR | H52: 3045000 | I52: =IFERROR(_xlfn.XLOOKUP(G52,FX_Rates!$C$11:$C$22,FX_Rates!$E$11:$E$22),1) -> 0.948 | J52: =H52*I52*K52 -> 2886660 | K52: 1
B53: 5 | C53: =Global_Assumptions!$C$8+((B53-1)*7) -> 46030 | D53: =C53+6 -> 46036 | E53: Operating Expenses | F53: Technology & Infrastructure | G53: USD | H53: 2537500 | I53: =IFERROR(_xlfn.XLOOKUP(G53,FX_Rates!$C$11:$C$22,FX_Rates!$E$11:$E$22),1) -> 1 | J53: =H53*I53*K53 -> 2537500 | K53: 1
B54: 5 | C54: =Global_Assumptions!$C$8+((B54-1)*7) -> 46030 | D54: =C54+6 -> 46036 | E54: Operating Expenses | F54: Marketing | G54: USD | H54: 1522500 | I54: =IFERROR(_xlfn.XLOOKUP(G54,FX_Rates!$C$11:$C$22,FX_Rates!$E$11:$E$22),1) -> 1 | J54: =H54*I54*K54 -> 1522500 | K54: 1
B55: 5 | C55: =Global_Assumptions!$C$8+((B55-1)*7) -> 46030 | D55: =C55+6 -> 46036 | E55: Operating Expenses | F55: G&A | G55: USD | H55: 1015000 | I55: =IFERROR(_xlfn.XLOOKUP(G55,FX_Rates!$C$11:$C$22,FX_Rates!$E$11:$E$22),1) -> 1 | J55: =H55*I55*K55 -> 1015000 | K55: 1
B56: 5 | C56: =Global_Assumptions!$C$8+((B56-1)*7) -> 46030 | D56: =C56+6 -> 46036 | E56: Payroll | F56: US Payroll | G56: USD | H56: 4060000 | I56: =IFERROR(_xlfn.XLOOKUP(G56,FX_Rates!$C$11:$C$22,FX_Rates!$E$11:$E$22),1) -> 1 | J56: =H56*I56*K56 -> 4060000 | K56: 1
B57: 5 | C57: =Global_Assumptions!$C$8+((B57-1)*7) -> 46030 | D57: =C57+6 -> 46036 | E57: Payroll | F57: International Payroll | G57: GBP | H57: 812000 | I57: =IFERROR(_xlfn.XLOOKUP(G57,FX_Rates!$C$11:$C$22,FX_Rates!$E$11:$E$22),1) -> 0.792 | J57: =H57*I57*K57 -> 643104 | K57: 1
B58: 5 | C58: =Global_Assumptions!$C$8+((B58-1)*7) -> 46030 | D58: =C58+6 -> 46036 | E58: Taxes | F58: Income Tax | G58: USD | H58: 2030000 | I58: =IFERROR(_xlfn.XLOOKUP(G58,FX_Rates!$C$11:$C$22,FX_Rates!$E$11:$E$22),1) -> 1 | J58: =H58*I58*K58 -> 2030000 | K58: 1
B59: 5 | C59: =Global_Assumptions!$C$8+((B59-1)*7) -> 46030 | D59: =C59+6 -> 46036 | E59: Debt Service | F59: Interest Payments | G59: USD | H59: 507500 | I59: =IFERROR(_xlfn.XLOOKUP(G59,FX_Rates!$C$11:$C$22,FX_Rates!$E$11:$E$22),1) -> 1 | J59: =H59*I59*K59 -> 507500 | K59: 1
A60: x | B60: 6 | C60: =Global_Assumptions!$C$8+((B60-1)*7) -> 46037 | D60: =C60+6 -> 46043 | E60: Settlements | F60: Merchant Payouts | G60: USD | H60: 19700000 | I60: =IFERROR(_xlfn.XLOOKUP(G60,FX_Rates!$C$11:$C$22,FX_Rates!$E$11:$E$22),1) -> 1 | J60: =H60*I60*K60 -> 19700000 | K60: 1
B61: 6 | C61: =Global_Assumptions!$C$8+((B61-1)*7) -> 46037 | D61: =C61+6 -> 46043 | E61: Settlements | F61: Partner Payments | G61: USD | H61: 7880000 | I61: =IFERROR(_xlfn.XLOOKUP(G61,FX_Rates!$C$11:$C$22,FX_Rates!$E$11:$E$22),1) -> 1 | J61: =H61*I61*K61 -> 7880000 | K61: 1
B62: 6 | C62: =Global_Assumptions!$C$8+((B62-1)*7) -> 46037 | D62: =C62+6 -> 46043 | E62: Settlements | F62: International Payouts | G62: EUR | H62: 2955000 | I62: =IFERROR(_xlfn.XLOOKUP(G62,FX_Rates!$C$11:$C$22,FX_Rates!$E$11:$E$22),1) -> 0.948 | J62: =H62*I62*K62 -> 2801340 | K62: 1
B63: 6 | C63: =Global_Assumptions!$C$8+((B63-1)*7) -> 46037 | D63: =C63+6 -> 46043 | E63: Operating Expenses | F63: Technology & Infrastructure | G63: USD | H63: 2462500 | I63: =IFERROR(_xlfn.XLOOKUP(G63,FX_Rates!$C$11:$C$22,FX_Rates!$E$11:$E$22),1) -> 1 | J63: =H63*I63*K63 -> 2462500 | K63: 1
B64: 6 | C64: =Global_Assumptions!$C$8+((B64-1)*7) -> 46037 | D64: =C64+6 -> 46043 | E64: Operating Expenses | F64: Marketing | G64: USD | H64: 1477500 | I64: =IFERROR(_xlfn.XLOOKUP(G64,FX_Rates!$C$11:$C$22,FX_Rates!$E$11:$E$22),1) -> 1 | J64: =H64*I64*K64 -> 1477500 | K64: 1
B65: 6 | C65: =Global_Assumptions!$C$8+((B65-1)*7) -> 46037 | D65: =C65+6 -> 46043 | E65: Operating Expenses | F65: G&A | G65: USD | H65: 985000 | I65: =IFERROR(_xlfn.XLOOKUP(G65,FX_Rates!$C$11:$C$22,FX_Rates!$E$11:$E$22),1) -> 1 | J65: =H65*I65*K65 -> 985000 | K65: 1
B66: 6 | C66: =Global_Assumptions!$C$8+((B66-1)*7) -> 46037 | D66: =C66+6 -> 46043 | E66: Payroll | F66: US Payroll | G66: USD | H66: 9850000 | I66: =IFERROR(_xlfn.XLOOKUP(G66,FX_Rates!$C$11:$C$22,FX_Rates!$E$11:$E$22),1) -> 1 | J66: =H66*I66*K66 -> 9850000 | K66: 1
B67: 6 | C67: =Global_Assumptions!$C$8+((B67-1)*7) -> 46037 | D67: =C67+6 -> 46043 | E67: Payroll | F67: International Payroll | G67: GBP | H67: 1970000 | I67: =IFERROR(_xlfn.XLOOKUP(G67,FX_Rates!$C$11:$C$22,FX_Rates!$E$11:$E$22),1) -> 0.792 | J67: =H67*I67*K67 -> 1560240 | K67: 1
B68: 6 | C68: =Global_Assumptions!$C$8+((B68-1)*7) -> 46037 | D68: =C68+6 -> 46043 | E68: Taxes | F68: Income Tax | G68: USD | H68: 1970000 | I68: =IFERROR(_xlfn.XLOOKUP(G68,FX_Rates!$C$11:$C$22,FX_Rates!$E$11:$E$22),1) -> 1 | J68: =H68*I68*K68 -> 1970000 | K68: 1
B69: 6 | C69: =Global_Assumptions!$C$8+((B69-1)*7) -> 46037 | D69: =C69+6 -> 46043 | E69: Debt Service | F69: Interest Payments | G69: USD | H69: 492500 | I69: =IFERROR(_xlfn.XLOOKUP(G69,FX_Rates!$C$11:$C$22,FX_Rates!$E$11:$E$22),1) -> 1 | J69: =H69*I69*K69 -> 492500 | K69: 1
A70: x | B70: 7 | C70: =Global_Assumptions!$C$8+((B70-1)*7) -> 46044 | D70: =C70+6 -> 46050 | E70: Settlements | F70: Merchant Payouts | G70: USD | H70: 20000000 | I70: =IFERROR(_xlfn.XLOOKUP(G70,FX_Rates!$C$11:$C$22,FX_Rates!$E$11:$E$22),1) -> 1 | J70: =H70*I70*K70 -> 20000000 | K70: 1
B71: 7 | C71: =Global_Assumptions!$C$8+((B71-1)*7) -> 46044 | D71: =C71+6 -> 46050 | E71: Settlements | F71: Partner Payments | G71: USD | H71: 8000000 | I71: =IFERROR(_xlfn.XLOOKUP(G71,FX_Rates!$C$11:$C$22,FX_Rates!$E$11:$E$22),1) -> 1 | J71: =H71*I71*K71 -> 8000000 | K71: 1
B72: 7 | C72: =Global_Assumptions!$C$8+((B72-1)*7) -> 46044 | D72: =C72+6 -> 46050 | E72: Settlements | F72: International Payouts | G72: EUR | H72: 3000000 | I72: =IFERROR(_xlfn.XLOOKUP(G72,FX_Rates!$C$11:$C$22,FX_Rates!$E$11:$E$22),1) -> 0.948 | J72: =H72*I72*K72 -> 2844000 | K72: 1
B73: 7 | C73: =Global_Assumptions!$C$8+((B73-1)*7) -> 46044 | D73: =C73+6 -> 46050 | E73: Operating Expenses | F73: Technology & Infrastructure | G73: USD | H73: 2500000 | I73: =IFERROR(_xlfn.XLOOKUP(G73,FX_Rates!$C$11:$C$22,FX_Rates!$E$11:$E$22),1) -> 1 | J73: =H73*I73*K73 -> 2500000 | K73: 1
B74: 7 | C74: =Global_Assumptions!$C$8+((B74-1)*7) -> 46044 | D74: =C74+6 -> 46050 | E74: Operating Expenses | F74: Marketing | G74: USD | H74: 1500000 | I74: =IFERROR(_xlfn.XLOOKUP(G74,FX_Rates!$C$11:$C$22,FX_Rates!$E$11:$E$22),1) -> 1 | J74: =H74*I74*K74 -> 1500000 | K74: 1
B75: 7 | C75: =Global_Assumptions!$C$8+((B75-1)*7) -> 46044 | D75: =C75+6 -> 46050 | E75: Operating Expenses | F75: G&A | G75: USD | H75: 1000000 | I75: =IFERROR(_xlfn.XLOOKUP(G75,FX_Rates!$C$11:$C$22,FX_Rates!$E$11:$E$22),1) -> 1 | J75: =H75*I75*K75 -> 1000000 | K75: 1
B76: 7 | C76: =Global_Assumptions!$C$8+((B76-1)*7) -> 46044 | D76: =C76+6 -> 46050 | E76: Payroll | F76: US Payroll | G76: USD | H76: 4000000 | I76: =IFERROR(_xlfn.XLOOKUP(G76,FX_Rates!$C$11:$C$22,FX_Rates!$E$11:$E$22),1) -> 1 | J76: =H76*I76*K76 -> 4000000 | K76: 1
B77: 7 | C77: =Global_Assumptions!$C$8+((B77-1)*7) -> 46044 | D77: =C77+6 -> 46050 | E77: Payroll | F77: International Payroll | G77: GBP | H77: 800000 | I77: =IFERROR(_xlfn.XLOOKUP(G77,FX_Rates!$C$11:$C$22,FX_Rates!$E$11:$E$22),1) -> 0.792 | J77: =H77*I77*K77 -> 633600 | K77: 1
B78: 7 | C78: =Global_Assumptions!$C$8+((B78-1)*7) -> 46044 | D78: =C78+6 -> 46050 | E78: Taxes | F78: Income Tax | G78: USD | H78: 2000000 | I78: =IFERROR(_xlfn.XLOOKUP(G78,FX_Rates!$C$11:$C$22,FX_Rates!$E$11:$E$22),1) -> 1 | J78: =H78*I78*K78 -> 2000000 | K78: 1
B79: 7 | C79: =Global_Assumptions!$C$8+((B79-1)*7) -> 46044 | D79: =C79+6 -> 46050 | E79: Debt Service | F79: Interest Payments | G79: USD | H79: 500000 | I79: =IFERROR(_xlfn.XLOOKUP(G79,FX_Rates!$C$11:$C$22,FX_Rates!$E$11:$E$22),1) -> 1 | J79: =H79*I79*K79 -> 500000 | K79: 1
A80: x | B80: 8 | C80: =Global_Assumptions!$C$8+((B80-1)*7) -> 46051 | D80: =C80+6 -> 46057 | E80: Settlements | F80: Merchant Payouts | G80: USD | H80: 20300000 | I80: =IFERROR(_xlfn.XLOOKUP(G80,FX_Rates!$C$11:$C$22,FX_Rates!$E$11:$E$22),1) -> 1 | J80: =H80*I80*K80 -> 20300000 | K80: 1
B81: 8 | C81: =Global_Assumptions!$C$8+((B81-1)*7) -> 46051 | D81: =C81+6 -> 46057 | E81: Settlements | F81: Partner Payments | G81: USD | H81: 8120000 | I81: =IFERROR(_xlfn.XLOOKUP(G81,FX_Rates!$C$11:$C$22,FX_Rates!$E$11:$E$22),1) -> 1 | J81: =H81*I81*K81 -> 8120000 | K81: 1
B82: 8 | C82: =Global_Assumptions!$C$8+((B82-1)*7) -> 46051 | D82: =C82+6 -> 46057 | E82: Settlements | F82: International Payouts | G82: EUR | H82: 3045000 | I82: =IFERROR(_xlfn.XLOOKUP(G82,FX_Rates!$C$11:$C$22,FX_Rates!$E$11:$E$22),1) -> 0.948 | J82: =H82*I82*K82 -> 2886660 | K82: 1
B83: 8 | C83: =Global_Assumptions!$C$8+((B83-1)*7) -> 46051 | D83: =C83+6 -> 46057 | E83: Operating Expenses | F83: Technology & Infrastructure | G83: USD | H83: 2537500 | I83: =IFERROR(_xlfn.XLOOKUP(G83,FX_Rates!$C$11:$C$22,FX_Rates!$E$11:$E$22),1) -> 1 | J83: =H83*I83*K83 -> 2537500 | K83: 1
B84: 8 | C84: =Global_Assumptions!$C$8+((B84-1)*7) -> 46051 | D84: =C84+6 -> 46057 | E84: Operating Expenses | F84: Marketing | G84: USD | H84: 1522500 | I84: =IFERROR(_xlfn.XLOOKUP(G84,FX_Rates!$C$11:$C$22,FX_Rates!$E$11:$E$22),1) -> 1 | J84: =H84*I84*K84 -> 1522500 | K84: 1
B85: 8 | C85: =Global_Assumptions!$C$8+((B85-1)*7) -> 46051 | D85: =C85+6 -> 46057 | E85: Operating Expenses | F85: G&A | G85: USD | H85: 1015000 | I85: =IFERROR(_xlfn.XLOOKUP(G85,FX_Rates!$C$11:$C$22,FX_Rates!$E$11:$E$22),1) -> 1 | J85: =H85*I85*K85 -> 1015000 | K85: 1
B86: 8 | C86: =Global_Assumptions!$C$8+((B86-1)*7) -> 46051 | D86: =C86+6 -> 46057 | E86: Payroll | F86: US Payroll | G86: USD | H86: 10150000 | I86: =IFERROR(_xlfn.XLOOKUP(G86,FX_Rates!$C$11:$C$22,FX_Rates!$E$11:$E$22),1) -> 1 | J86: =H86*I86*K86 -> 10150000 | K86: 1
B87: 8 | C87: =Global_Assumptions!$C$8+((B87-1)*7) -> 46051 | D87: =C87+6 -> 46057 | E87: Payroll | F87: International Payroll | G87: GBP | H87: 2030000 | I87: =IFERROR(_xlfn.XLOOKUP(G87,FX_Rates!$C$11:$C$22,FX_Rates!$E$11:$E$22),1) -> 0.792 | J87: =H87*I87*K87 -> 1607760 | K87: 1
B88: 8 | C88: =Global_Assumptions!$C$8+((B88-1)*7) -> 46051 | D88: =C88+6 -> 46057 | E88: Taxes | F88: Income Tax | G88: USD | H88: 2030000 | I88: =IFERROR(_xlfn.XLOOKUP(G88,FX_Rates!$C$11:$C$22,FX_Rates!$E$11:$E$22),1) -> 1 | J88: =H88*I88*K88 -> 2030000 | K88: 1
B89: 8 | C89: =Global_Assumptions!$C$8+((B89-1)*7) -> 46051 | D89: =C89+6 -> 46057 | E89: Debt Service | F89: Interest Payments | G89: USD | H89: 507500 | I89: =IFERROR(_xlfn.XLOOKUP(G89,FX_Rates!$C$11:$C$22,FX_Rates!$E$11:$E$22),1) -> 1 | J89: =H89*I89*K89 -> 507500 | K89: 1
A90: x | B90: 9 | C90: =Global_Assumptions!$C$8+((B90-1)*7) -> 46058 | D90: =C90+6 -> 46064 | E90: Settlements | F90: Merchant Payouts | G90: USD | H90: 19700000 | I90: =IFERROR(_xlfn.XLOOKUP(G90,FX_Rates!$C$11:$C$22,FX_Rates!$E$11:$E$22),1) -> 1 | J90: =H90*I90*K90 -> 19700000 | K90: 1
B91: 9 | C91: =Global_Assumptions!$C$8+((B91-1)*7) -> 46058 | D91: =C91+6 -> 46064 | E91: Settlements | F91: Partner Payments | G91: USD | H91: 7880000 | I91: =IFERROR(_xlfn.XLOOKUP(G91,FX_Rates!$C$11:$C$22,FX_Rates!$E$11:$E$22),1) -> 1 | J91: =H91*I91*K91 -> 7880000 | K91: 1
B92: 9 | C92: =Global_Assumptions!$C$8+((B92-1)*7) -> 46058 | D92: =C92+6 -> 46064 | E92: Settlements | F92: International Payouts | G92: EUR | H92: 2955000 | I92: =IFERROR(_xlfn.XLOOKUP(G92,FX_Rates!$C$11:$C$22,FX_Rates!$E$11:$E$22),1) -> 0.948 | J92: =H92*I92*K92 -> 2801340 | K92: 1
B93: 9 | C93: =Global_Assumptions!$C$8+((B93-1)*7) -> 46058 | D93: =C93+6 -> 46064 | E93: Operating Expenses | F93: Technology & Infrastructure | G93: USD | H93: 2462500 | I93: =IFERROR(_xlfn.XLOOKUP(G93,FX_Rates!$C$11:$C$22,FX_Rates!$E$11:$E$22),1) -> 1 | J93: =H93*I93*K93 -> 2462500 | K93: 1
B94: 9 | C94: =Global_Assumptions!$C$8+((B94-1)*7) -> 46058 | D94: =C94+6 -> 46064 | E94: Operating Expenses | F94: Marketing | G94: USD | H94: 1477500 | I94: =IFERROR(_xlfn.XLOOKUP(G94,FX_Rates!$C$11:$C$22,FX_Rates!$E$11:$E$22),1) -> 1 | J94: =H94*I94*K94 -> 1477500 | K94: 1
B95: 9 | C95: =Global_Assumptions!$C$8+((B95-1)*7) -> 46058 | D95: =C95+6 -> 46064 | E95: Operating Expenses | F95: G&A | G95: USD | H95: 985000 | I95: =IFERROR(_xlfn.XLOOKUP(G95,FX_Rates!$C$11:$C$22,FX_Rates!$E$11:$E$22),1) -> 1 | J95: =H95*I95*K95 -> 985000 | K95: 1
B96: 9 | C96: =Global_Assumptions!$C$8+((B96-1)*7) -> 46058 | D96: =C96+6 -> 46064 | E96: Payroll | F96: US Payroll | G96: USD | H96: 3940000 | I96: =IFERROR(_xlfn.XLOOKUP(G96,FX_Rates!$C$11:$C$22,FX_Rates!$E$11:$E$22),1) -> 1 | J96: =H96*I96*K96 -> 3940000 | K96: 1
B97: 9 | C97: =Global_Assumptions!$C$8+((B97-1)*7) -> 46058 | D97: =C97+6 -> 46064 | E97: Payroll | F97: International Payroll | G97: GBP | H97: 788000 | I97: =IFERROR(_xlfn.XLOOKUP(G97,FX_Rates!$C$11:$C$22,FX_Rates!$E$11:$E$22),1) -> 0.792 | J97: =H97*I97*K97 -> 624096 | K97: 1
B98: 9 | C98: =Global_Assumptions!$C$8+((B98-1)*7) -> 46058 | D98: =C98+6 -> 46064 | E98: Taxes | F98: Income Tax | G98: USD | H98: 1970000 | I98: =IFERROR(_xlfn.XLOOKUP(G98,FX_Rates!$C$11:$C$22,FX_Rates!$E$11:$E$22),1) -> 1 | J98: =H98*I98*K98 -> 1970000 | K98: 1
B99: 9 | C99: =Global_Assumptions!$C$8+((B99-1)*7) -> 46058 | D99: =C99+6 -> 46064 | E99: Debt Service | F99: Interest Payments | G99: USD | H99: 492500 | I99: =IFERROR(_xlfn.XLOOKUP(G99,FX_Rates!$C$11:$C$22,FX_Rates!$E$11:$E$22),1) -> 1 | J99: =H99*I99*K99 -> 492500 | K99: 1
A100: x | B100: 10 | C100: =Global_Assumptions!$C$8+((B100-1)*7) -> 46065 | D100: =C100+6 -> 46071 | E100: Settlements | F100: Merchant Payouts | G100: USD | H100: 20000000 | I100: =IFERROR(_xlfn.XLOOKUP(G100,FX_Rates!$C$11:$C$22,FX_Rates!$E$11:$E$22),1) -> 1 | J100: =H100*I100*K100 -> 20000000 | K100: 1
B101: 10 | C101: =Global_Assumptions!$C$8+((B101-1)*7) -> 46065 | D101: =C101+6 -> 46071 | E101: Settlements | F101: Partner Payments | G101: USD | H101: 8000000 | I101: =IFERROR(_xlfn.XLOOKUP(G101,FX_Rates!$C$11:$C$22,FX_Rates!$E$11:$E$22),1) -> 1 | J101: =H101*I101*K101 -> 8000000 | K101: 1
B102: 10 | C102: =Global_Assumptions!$C$8+((B102-1)*7) -> 46065 | D102: =C102+6 -> 46071 | E102: Settlements | F102: International Payouts | G102: EUR | H102: 3000000 | I102: =IFERROR(_xlfn.XLOOKUP(G102,FX_Rates!$C$11:$C$22,FX_Rates!$E$11:$E$22),1) -> 0.948 | J102: =H102*I102*K102 -> 2844000 | K102: 1
B103: 10 | C103: =Global_Assumptions!$C$8+((B103-1)*7) -> 46065 | D103: =C103+6 -> 46071 | E103: Operating Expenses | F103: Technology & Infrastructure | G103: USD | H103: 2500000 | I103: =IFERROR(_xlfn.XLOOKUP(G103,FX_Rates!$C$11:$C$22,FX_Rates!$E$11:$E$22),1) -> 1 | J103: =H103*I103*K103 -> 2500000 | K103: 1
...

Sheet 13W_Cash_Forecast
B2: 13-WEEK ROLLING CASH FORECAST
B3: Core Calculation Sheet
B5: FORECAST PARAMETERS | F5: 13 WEEK TOTAL
B6: Base Currency: | C6: {=Global_Assumptions!C7} -> USD | F6: (+) Inflows | G6: =SUM(D15:P15) -> 649162260
B7: Forecast Start: | C7: {=Global_Assumptions!C8} -> 46002 | F7: (-) Outflows | G7: =SUM(D16:P16) -> 604411200
B8: Minimum Liquidity: | C8: {=Global_Assumptions!C31} -> 50000000 | F8: (=) Net Cash | G8: =SUM(D17:P17) -> 44751060
B9: Week 0 Balance (Actual): | C9: =SUMIF(Cash_Balances_Actuals!$H$10:$H$17,"USD",Cash_Balances_Actuals!$J$10:$J$17) -> 89700000 | F9: (=) Ending Cash | G9: {=P18} -> 134451060
B11: WEEKLY CASH FORECAST
C12: Week 0 | D12: Week 1 | E12: Week 2 | F12: Week 3 | G12: Week 4 | H12: Week 5 | I12: Week 6 | J12: Week 7 | K12: Week 8 | L12: Week 9 | M12: Week 10 | N12: Week 11 | O12: Week 12 | P12: Week 13
B13: Week Ending | C13: =C7-1 -> 46001 | D13: =C7+(1*7)-1 -> 46008 | E13: =C7+(2*7)-1 -> 46015 | F13: =C7+(3*7)-1 -> 46022 | G13: =C7+(4*7)-1 -> 46029 | H13: =C7+(5*7)-1 -> 46036 | I13: =C7+(6*7)-1 -> 46043 | J13: =C7+(7*7)-1 -> 46050 | K13: =C7+(8*7)-1 -> 46057 | L13: =C7+(9*7)-1 -> 46064 | M13: =C7+(10*7)-1 -> 46071 | N13: =C7+(11*7)-1 -> 46078 | O13: =C7+(12*7)-1 -> 46085 | P13: =C7+(13*7)-1 -> 46092
B14: Opening Cash Balance | C14: =C9 -> 89700000 | D14: {=C18} -> 89700000 | E14: {=D18} -> 96196660 | F14: {=E18} -> 95993480 | G14: {=F18} -> 105133764 | H14: {=G18} -> 99680544 | I14: {=H18} -> 105532540 | J14: {=I18} -> 106827200 | K14: {=J18} -> 115322820 | ... P14: {=O18} -> 127954400
B15: (+) Total Inflows | C15: 0 | D15: =SUMIF(Cash_Inflows!$B$10:$B$100,1,Cash_Inflows!$J$10:$J$100) -> 49474260 | E15: =SUMIF(Cash_Inflows!$B$10:$B$100,2,Cash_Inflows!$J$10:$J$100) -> 50473740 | F15: =SUMIF(Cash_Inflows!$B$10:$B$100,3,Cash_Inflows!$J$10:$J$100) -> 51473220 | G15: =SUMIF(Cash_Inflows!$B$10:$B$100,4,Cash_Inflows!$J$10:$J$100) -> 48474780 | H15: =SUMIF(Cash_Inflows!$B$10:$B$100,5,Cash_Inflows!$J$10:$J$100) -> 49474260 | I15: =SUMIF(Cash_Inflows!$B$10:$B$100,6,Cash_Inflows!$J$10:$J$100) -> 50473740 | J15: =SUMIF(Cash_Inflows!$B$10:$B$100,7,Cash_Inflows!$J$10:$J$100) -> 51473220 | K15: =SUMIF(Cash_Inflows!$B$10:$B$100,8,Cash_Inflows!$J$10:$J$100) -> 48474780 | L15: =SUMIF(Cash_Inflows!$B$10:$B$100,9,Cash_Inflows!$J$10:$J$100) -> 49474260 | M15: =SUMIF(Cash_Inflows!$B$10:$B$100,10,Cash_Inflows!$J$10:$J$100) -> 50473740 | N15: =SUMIF(Cash_Inflows!$B$10:$B$100,11,Cash_Inflows!$J$10:$J$100) -> 51473220 | O15: =SUMIF(Cash_Inflows!$B$10:$B$100,12,Cash_Inflows!$J$10:$J$100) -> 48474780 | P15: =SUMIF(Cash_Inflows!$B$10:$B$100,13,Cash_Inflows!$J$10:$J$100) -> 49474260
B16: (-) Total Outflows | C16: 0 | D16: =SUMIF(Cash_Outflows!$B$10:$B$139,1,Cash_Outflows!$J$10:$J$139) -> 42977600 | E16: =SUMIF(Cash_Outflows!$B$10:$B$139,2,Cash_Outflows!$J$10:$J$139) -> 50676920 | F16: =SUMIF(Cash_Outflows!$B$10:$B$139,3,Cash_Outflows!$J$10:$J$139) -> 42332936 | G16: =SUMIF(Cash_Outflows!$B$10:$B$139,4,Cash_Outflows!$J$10:$J$139) -> 53928000 | H16: =SUMIF(Cash_Outflows!$B$10:$B$139,5,Cash_Outflows!$J$10:$J$139) -> 43622264 | I16: =SUMIF(Cash_Outflows!$B$10:$B$139,6,Cash_Outflows!$J$10:$J$139) -> 49179080 | J16: =SUMIF(Cash_Outflows!$B$10:$B$139,7,Cash_Outflows!$J$10:$J$139) -> 42977600 | K16: =SUMIF(Cash_Outflows!$B$10:$B$139,8,Cash_Outflows!$J$10:$J$139) -> 50676920 | L16: =SUMIF(Cash_Outflows!$B$10:$B$139,9,Cash_Outflows!$J$10:$J$139) -> 42332936 | M16: =SUMIF(Cash_Outflows!$B$10:$B$139,10,Cash_Outflows!$J$10:$J$139) -> 49928000 | N16: =SUMIF(Cash_Outflows!$B$10:$B$139,11,Cash_Outflows!$J$10:$J$139) -> 43622264 | O16: =SUMIF(Cash_Outflows!$B$10:$B$139,12,Cash_Outflows!$J$10:$J$139) -> 49179080 | P16: =SUMIF(Cash_Outflows!$B$10:$B$139,13,Cash_Outflows!$J$10:$J$139) -> 42977600
B17: (=) Net Cash Movement | C17: =C15-C16 -> 0 | D17: =D15-D16 -> 6496660 | E17: =E15-E16 -> -203180 | F17: =F15-F16 -> 9140284 | G17: =G15-G16 -> -5453220 | H17: =H15-H16 -> 5851996 | I17: =I15-I16 -> 1294660 | J17: =J15-J16 -> 8495620 | ... P17: =P15-P16 -> 6496660
B18: (=) Ending Cash Balance | C18: =C14+C17 -> 89700000 | D18: =D14+D17 -> 96196660 | E18: =E14+E17 -> 95993480 | F18: =F14+F17 -> 105133764 | G18: =G14+G17 -> 99680544 | H18: =H14+H17 -> 105532540 | I18: =I14+I17 -> 106827200 | J18: =J14+J17 -> 115322820 | ... P18: =P14+P17 -> 134451060
B20: Minimum Liquidity Buffer | C20: {=$C$8} -> 50000000 | D20: {=$C$8} -> 50000000 | E20: {=$C$8} -> 50000000 | F20: {=$C$8} -> 50000000 | G20: {=$C$8} -> 50000000 | H20: {=$C$8} -> 50000000 | I20: {=$C$8} -> 50000000 | J20: {=$C$8} -> 50000000 | ... P20: {=$C$8} -> 50000000
B21: Buffer Surplus/(Deficit) | C21: =C18-C20 -> 39700000 | D21: =D18-D20 -> 46196660 | E21: =E18-E20 -> 45993480 | F21: =F18-F20 -> 55133764 | G21: =G18-G20 -> 49680544 | H21: =H18-H20 -> 55532540 | I21: =I18-I20 -> 56827200 | J21: =J18-J20 -> 65322820 | ... P21: =P18-P20 -> 84451060
B22: Liquidity Test | C22: =IF(C21>=0,"PASS","FAIL") -> PASS | D22: =IF(D21>=0,"PASS","FAIL") -> PASS | E22: =IF(E21>=0,"PASS","FAIL") -> PASS | F22: =IF(F21>=0,"PASS","FAIL") -> PASS | G22: =IF(G21>=0,"PASS","FAIL") -> PASS | H22: =IF(H21>=0,"PASS","FAIL") -> PASS | I22: =IF(I21>=0,"PASS","FAIL") -> PASS | J22: =IF(J21>=0,"PASS","FAIL") -> PASS | ... P22: =IF(P21>=0,"PASS","FAIL") -> PASS

Sheet FX_Exposure
B2: FX EXPOSURE & TRANSLATION
B3: Currency Risk Analysis and Sensitity Training
B5: CURRENT FX POSITIONS (from Cash Balances)
B6: Currency | C6: Balance (Local) | D6: FX Rate | E6: Balance (USD) | F6: % of Total
B7: USD | C7: =SUMIF(Cash_Balances_Actuals!$H$10:$H$17,B7,Cash_Balances_Actuals!$J$10:$J$17) -> 89700000 | D7: =IFERROR(_xlfn.XLOOKUP(B7,FX_Rates!$C$11:$C$22,FX_Rates!$E$11:$E$22),1) -> 1 | E7: =C7*D7 -> 89700000 | F7: =E7/$E$11 -> 0.67939928
B8: EUR | C8: =SUMIF(Cash_Balances_Actuals!$H$10:$H$17,B8,Cash_Balances_Actuals!$J$10:$J$17) -> 20000000 | D8: =IFERROR(_xlfn.XLOOKUP(B8,FX_Rates!$C$11:$C$22,FX_Rates!$E$11:$E$22),1) -> 0.948 | E8: =C8*D8 -> 18960000 | F8: =E8/$E$11 -> 0.14360547
B9: GBP | C9: =SUMIF(Cash_Balances_Actuals!$H$10:$H$17,B9,Cash_Balances_Actuals!$J$10:$J$17) -> 12900000 | D9: =IFERROR(_xlfn.XLOOKUP(B9,FX_Rates!$C$11:$C$22,FX_Rates!$E$11:$E$22),1) -> 0.792 | E9: =C9*D9 -> 10216800 | F9: =E9/$E$11 -> 0.077383351
B10: SGD | C10: =SUMIF(Cash_Balances_Actuals!$H$10:$H$17,B10,Cash_Balances_Actuals!$J$10:$J$17) -> 9800000 | D10: =IFERROR(_xlfn.XLOOKUP(B10,FX_Rates!$C$11:$C$22,FX_Rates!$E$11:$E$22),1) -> 1.342 | E10: =C10*D10 -> 13151600 | F10: =E10/$E$11 -> 0.099611902
B11: TOTAL (USD) | E11: =SUM(E7:E10) -> 132028400 | F11: 1
B13: FX SENSITIVITY ANALYSIS
B14: Currency | C14: Current USD Value | D14: 1% FX Shock | E14: 5% FX Shock | F14: 10% FX Shock | G14: Max Risk (10%)
B15: EUR | C15: =SUMIF(Cash_Balances_Actuals!$H$10:$H$17,B15,Cash_Balances_Actuals!$J$10:$J$17)*_xlfn.XLOOKUP(B15,FX_Rates!$C$11:$C$22,FX_Rates!$E$11:$E$22) -> 18960000 | D15: =C15*(1+Global_Assumptions!$C$25) -> 18770400 | E15: =C15*(1+Global_Assumptions!$C$26) -> 18012000 | F15: =C15*(1+Global_Assumptions!$C$27) -> 17064000 | G15: =C15-F15 -> 1896000
B16: GBP | C16: =SUMIF(Cash_Balances_Actuals!$H$10:$H$17,B16,Cash_Balances_Actuals!$J$10:$J$17)*_xlfn.XLOOKUP(B16,FX_Rates!$C$11:$C$22,FX_Rates!$E$11:$E$22) -> 10216800 | D16: =C16*(1+Global_Assumptions!$C$25) -> 10114632 | E16: =C16*(1+Global_Assumptions!$C$26) -> 9705960 | F16: =C16*(1+Global_Assumptions!$C$27) -> 9195120 | G16: =C16-F16 -> 1021680
B17: SGD | C17: =SUMIF(Cash_Balances_Actuals!$H$10:$H$17,B17,Cash_Balances_Actuals!$J$10:$J$17)*_xlfn.XLOOKUP(B17,FX_Rates!$C$11:$C$22,FX_Rates!$E$11:$E$22) -> 13151600 | D17: =C17*(1+Global_Assumptions!$C$25) -> 13020084 | E17: =C17*(1+Global_Assumptions!$C$26) -> 12494020 | F17: =C17*(1+Global_Assumptions!$C$27) -> 11836440 | G17: =C17-F17 -> 1315160
B18: TOTAL IMPACT | C18: =SUM(C15:C17) -> 42328400 | D18: =SUM(D15:D17) -> 41905116 | E18: =SUM(E15:E17) -> 40211980 | F18: =SUM(F15:F17) -> 38095560 | G18: =SUM(G15:G17) -> 4232840
B19: Impact % of Total Cash | D19: =(D18-C18)/$E$11 -> -0.0032060072 | E19: =(E18-C18)/$E$11 -> -0.016030036 | F19: =(F18-C18)/$E$11 -> -0.032060072 | G19: =G18/$E$11 -> 0.032060072
B22: CURRENCY CONCENTRATION ANALYSIS
B23: Currency | C23: Current Position | D23: Concentration % | E23: Max Allowed (40%) | F23: Status
B24: USD | C24: {=E7} -> 89700000 | D24: =C24/$E$11 -> 0.67939928 | E24: {=Global_Assumptions!$C$33} -> 0.4 | F24: =IF(D24>E24,"EXCEEDS LIMIT","WITHIN LIMIT") -> EXCEEDS LIMIT
B25: EUR | C25: {=E8} -> 18960000 | D25: =C25/$E$11 -> 0.14360547 | E25: {=Global_Assumptions!$C$33} -> 0.4 | F25: =IF(D25>E25,"EXCEEDS LIMIT","WITHIN LIMIT") -> WITHIN LIMIT
B26: GBP | C26: {=E9} -> 10216800 | D26: =C26/$E$11 -> 0.077383351 | E26: {=Global_Assumptions!$C$33} -> 0.4 | F26: =IF(D26>E26,"EXCEEDS LIMIT","WITHIN LIMIT") -> WITHIN LIMIT
B27: SGD | C27: {=E10} -> 13151600 | D27: =C27/$E$11 -> 0.099611902 | E27: {=Global_Assumptions!$C$33} -> 0.4 | F27: =IF(D27>E27,"EXCEEDS LIMIT","WITHIN LIMIT") -> WITHIN LIMIT

Sheet Data_Link
A1: FX_Rates
A2: date,currency,rate_to_usd
A3: Fri Dec 05 2025 00:00:00 GMT+0000 (Coordinated Universal Time),AUD,0.6635
A4: Fri Dec 05 2025 00:00:00 GMT+0000 (Coordinated Universal Time),CAD,0.7216048491845866
A5: Fri Dec 05 2025 00:00:00 GMT+0000 (Coordinated Universal Time),CHF,1.2422360248447204
A6: Fri Dec 05 2025 00:00:00 GMT+0000 (Coordinated Universal Time),CNY,0.14145071856965033
A7: Fri Dec 05 2025 00:00:00 GMT+0000 (Coordinated Universal Time),EUR,1.1635
A8: Fri Dec 05 2025 00:00:00 GMT+0000 (Coordinated Universal Time),GBP,1.3324
A9: Fri Dec 05 2025 00:00:00 GMT+0000 (Coordinated Universal Time),INR,0.011114816049794377
A10: Fri Dec 05 2025 00:00:00 GMT+0000 (Coordinated Universal Time),JPY,0.00643915003219575
A11: Thu Dec 04 2025 00:00:00 GMT+0000 (Coordinated Universal Time),AUD,0.6619
A12: Thu Dec 04 2025 00:00:00 GMT+0000 (Coordinated Universal Time),CAD,0.7174115790228854
... A93942: Sat Jan 01 2000 00:00:00 GMT+0000 (Coordinated Universal Time),DFF,Federal Funds Effective Rate,0.039900000000000005
